{"action":{"identity":{"address":"N\u0000sourcecred\u0000core\u0000IDENTITY\u0000Cmurb2iMJGiKYk3avQV1Wg\u0000","aliases":[],"id":"Cmurb2iMJGiKYk3avQV1Wg","name":"Andy-Gray---KnownOrigin-Labs","subtype":"USER"},"type":"CREATE_IDENTITY"},"ledgerTimestamp":1675041002848,"uuid":"lA5zP6VsGOIzRYu5JFxGzQ","version":"1"}
{"action":{"alias":{"address":"N\u0000sourcecred\u0000discord\u0000MEMBER\u0000user\u0000107093550830727168\u0000","description":"discord/Andy Gray | KnownOrigin Labs#4821"},"identityId":"Cmurb2iMJGiKYk3avQV1Wg","type":"ADD_ALIAS"},"ledgerTimestamp":1675041002848,"uuid":"7OyCaln8e6amX5MiRUZR9A","version":"1"}
{"action":{"identity":{"address":"N\u0000sourcecred\u0000core\u0000IDENTITY\u0000Gp75Er7jEtP8h8MeAoQoQw\u0000","aliases":[],"id":"Gp75Er7jEtP8h8MeAoQoQw","name":"Substreight","subtype":"USER"},"type":"CREATE_IDENTITY"},"ledgerTimestamp":1675041002849,"uuid":"g5NI8sOPw8p7z3yZQ7LBGg","version":"1"}
{"action":{"alias":{"address":"N\u0000sourcecred\u0000discord\u0000MEMBER\u0000user\u0000116417042675924997\u0000","description":"discord/Substreight#8249"},"identityId":"Gp75Er7jEtP8h8MeAoQoQw","type":"ADD_ALIAS"},"ledgerTimestamp":1675041002850,"uuid":"eb9SpYwcM1VrfwsKJGogpw","version":"1"}
{"action":{"identity":{"address":"N\u0000sourcecred\u0000core\u0000IDENTITY\u0000PVqRvGB55wKKBWi9xQgcxw\u0000","aliases":[],"id":"PVqRvGB55wKKBWi9xQgcxw","name":"METADREAMER---","subtype":"USER"},"type":"CREATE_IDENTITY"},"ledgerTimestamp":1675041002850,"uuid":"CpEvlDGHZprSO748FoD18g","version":"1"}
{"action":{"alias":{"address":"N\u0000sourcecred\u0000discord\u0000MEMBER\u0000user\u0000118260545211072517\u0000","description":"discord/METADREAMER &#x1F419;#1111"},"identityId":"PVqRvGB55wKKBWi9xQgcxw","type":"ADD_ALIAS"},"ledgerTimestamp":1675041002850,"uuid":"Vpnpo3jOax8KxVA1um5bqQ","version":"1"}
{"action":{"identity":{"address":"N\u0000sourcecred\u0000core\u0000IDENTITY\u0000OfATjaLEBiEVQVe3CWmwcw\u0000","aliases":[],"id":"OfATjaLEBiEVQVe3CWmwcw","name":"garrett","subtype":"USER"},"type":"CREATE_IDENTITY"},"ledgerTimestamp":1675041002851,"uuid":"ud3OkyQlk4mvSzlfmb2t1Q","version":"1"}
{"action":{"alias":{"address":"N\u0000sourcecred\u0000discord\u0000MEMBER\u0000user\u0000132583578025328640\u0000","description":"discord/garrett#3503"},"identityId":"OfATjaLEBiEVQVe3CWmwcw","type":"ADD_ALIAS"},"ledgerTimestamp":1675041002851,"uuid":"qU7W6Ckh0EENZnLbByBRQA","version":"1"}
{"action":{"identity":{"address":"N\u0000sourcecred\u0000core\u0000IDENTITY\u0000V2E8vkG72TbUlgfalGds1w\u0000","aliases":[],"id":"V2E8vkG72TbUlgfalGds1w","name":"alphast0rm","subtype":"USER"},"type":"CREATE_IDENTITY"},"ledgerTimestamp":1675041002852,"uuid":"76k4i2Qb1q5VnSqEIDLsJw","version":"1"}
{"action":{"alias":{"address":"N\u0000sourcecred\u0000discord\u0000MEMBER\u0000user\u0000141006954880303105\u0000","description":"discord/alphast0rm#3577"},"identityId":"V2E8vkG72TbUlgfalGds1w","type":"ADD_ALIAS"},"ledgerTimestamp":1675041002852,"uuid":"ow8KQSqsYWfYyWrK7rPV9Q","version":"1"}
{"action":{"identity":{"address":"N\u0000sourcecred\u0000core\u0000IDENTITY\u00005r0UaBz9oNC91W3kYWfOag\u0000","aliases":[],"id":"5r0UaBz9oNC91W3kYWfOag","name":"Tom","subtype":"USER"},"type":"CREATE_IDENTITY"},"ledgerTimestamp":1675041002852,"uuid":"t2js4uLX1pa3CLqB5eIabA","version":"1"}
{"action":{"alias":{"address":"N\u0000sourcecred\u0000discord\u0000MEMBER\u0000user\u0000157400886874865664\u0000","description":"discord/Tom#5180"},"identityId":"5r0UaBz9oNC91W3kYWfOag","type":"ADD_ALIAS"},"ledgerTimestamp":1675041002853,"uuid":"UWtWQEZ8G02JJoUx47MjbA","version":"1"}
{"action":{"identity":{"address":"N\u0000sourcecred\u0000core\u0000IDENTITY\u0000cJX1sVj1YX7olWg7TyUDAg\u0000","aliases":[],"id":"cJX1sVj1YX7olWg7TyUDAg","name":"Tony","subtype":"USER"},"type":"CREATE_IDENTITY"},"ledgerTimestamp":1675041002853,"uuid":"z6OGUpljkgnlEE5qxnZWtQ","version":"1"}
{"action":{"alias":{"address":"N\u0000sourcecred\u0000discord\u0000MEMBER\u0000user\u0000163457318514720768\u0000","description":"discord/Tony#5838"},"identityId":"cJX1sVj1YX7olWg7TyUDAg","type":"ADD_ALIAS"},"ledgerTimestamp":1675041002853,"uuid":"j5KK5SRko6hrFlX1MWLmVA","version":"1"}
{"action":{"identity":{"address":"N\u0000sourcecred\u0000core\u0000IDENTITY\u0000OMDpCJ0XFXtzKt467Z8xjA\u0000","aliases":[],"id":"OMDpCJ0XFXtzKt467Z8xjA","name":"madcapslaugh","subtype":"USER"},"type":"CREATE_IDENTITY"},"ledgerTimestamp":1675041002853,"uuid":"gVyqsq8skNx5SPXGoAkrgA","version":"1"}
{"action":{"alias":{"address":"N\u0000sourcecred\u0000discord\u0000MEMBER\u0000user\u0000183833390569619456\u0000","description":"discord/madcapslaugh#8503"},"identityId":"OMDpCJ0XFXtzKt467Z8xjA","type":"ADD_ALIAS"},"ledgerTimestamp":1675041002853,"uuid":"pcDOyh3Qgg155v5S07TNGQ","version":"1"}
{"action":{"identity":{"address":"N\u0000sourcecred\u0000core\u0000IDENTITY\u00008VzArVa9AZVMwmxX8bpbYw\u0000","aliases":[],"id":"8VzArVa9AZVMwmxX8bpbYw","name":"Paxyn","subtype":"USER"},"type":"CREATE_IDENTITY"},"ledgerTimestamp":1675041002854,"uuid":"dd8T45dvEhnrGSwcxFRMkg","version":"1"}
{"action":{"alias":{"address":"N\u0000sourcecred\u0000discord\u0000MEMBER\u0000user\u0000184804183965302785\u0000","description":"discord/Paxyn#9421"},"identityId":"8VzArVa9AZVMwmxX8bpbYw","type":"ADD_ALIAS"},"ledgerTimestamp":1675041002854,"uuid":"DYsB6lgAsKoxxD0nF0LHpw","version":"1"}
{"action":{"identity":{"address":"N\u0000sourcecred\u0000core\u0000IDENTITY\u0000mERFmUXVETMewrXksmmzog\u0000","aliases":[],"id":"mERFmUXVETMewrXksmmzog","name":"Kispus","subtype":"USER"},"type":"CREATE_IDENTITY"},"ledgerTimestamp":1675041002854,"uuid":"7hOYlhBRWWHMsAnxyjSN1Q","version":"1"}
{"action":{"alias":{"address":"N\u0000sourcecred\u0000discord\u0000MEMBER\u0000user\u0000195566728766291978\u0000","description":"discord/Kispus#7924"},"identityId":"mERFmUXVETMewrXksmmzog","type":"ADD_ALIAS"},"ledgerTimestamp":1675041002854,"uuid":"NNR8NOnd1FM2QVjJaxjdcw","version":"1"}
{"action":{"identity":{"address":"N\u0000sourcecred\u0000core\u0000IDENTITY\u00005ulEy4RzZY3gvpJmltNjyA\u0000","aliases":[],"id":"5ulEy4RzZY3gvpJmltNjyA","name":"Ben-Middleton","subtype":"USER"},"type":"CREATE_IDENTITY"},"ledgerTimestamp":1675041002855,"uuid":"YYtKYgGKJllc1DZ3koXX2g","version":"1"}
{"action":{"alias":{"address":"N\u0000sourcecred\u0000discord\u0000MEMBER\u0000user\u0000234360516921786368\u0000","description":"discord/Ben Middleton#7011"},"identityId":"5ulEy4RzZY3gvpJmltNjyA","type":"ADD_ALIAS"},"ledgerTimestamp":1675041002855,"uuid":"KEmmrhG2C8kIqaAmzQQvkQ","version":"1"}
{"action":{"identity":{"address":"N\u0000sourcecred\u0000core\u0000IDENTITY\u0000w03osD2Ywhpu7abxORk9Vg\u0000","aliases":[],"id":"w03osD2Ywhpu7abxORk9Vg","name":"Lumberg","subtype":"USER"},"type":"CREATE_IDENTITY"},"ledgerTimestamp":1675041002855,"uuid":"3opEl8D66cNKLrRVXoSoBw","version":"1"}
{"action":{"alias":{"address":"N\u0000sourcecred\u0000discord\u0000MEMBER\u0000user\u0000264508693259878401\u0000","description":"discord/Lumberg#5510"},"identityId":"w03osD2Ywhpu7abxORk9Vg","type":"ADD_ALIAS"},"ledgerTimestamp":1675041002855,"uuid":"7nPCkRK9ubUDzYIaPnG5ZA","version":"1"}
{"action":{"identity":{"address":"N\u0000sourcecred\u0000core\u0000IDENTITY\u0000Zpu4wjmX2VzOPauOqBTkZg\u0000","aliases":[],"id":"Zpu4wjmX2VzOPauOqBTkZg","name":"Vlad---Reality-Cards","subtype":"USER"},"type":"CREATE_IDENTITY"},"ledgerTimestamp":1675041002856,"uuid":"Z8vWEBNUwLJv72SwWGJOkw","version":"1"}
{"action":{"alias":{"address":"N\u0000sourcecred\u0000discord\u0000MEMBER\u0000user\u0000275034221532282891\u0000","description":"discord/Vlad | Reality Cards#7011"},"identityId":"Zpu4wjmX2VzOPauOqBTkZg","type":"ADD_ALIAS"},"ledgerTimestamp":1675041002856,"uuid":"qKrPjEWTZ2MSKSM9t2w8zg","version":"1"}
{"action":{"identity":{"address":"N\u0000sourcecred\u0000core\u0000IDENTITY\u0000rrold5b97B5Ka6b2196BRw\u0000","aliases":[],"id":"rrold5b97B5Ka6b2196BRw","name":"ceresstation","subtype":"USER"},"type":"CREATE_IDENTITY"},"ledgerTimestamp":1675041002857,"uuid":"IOjsnNPzsplE7i979VELow","version":"1"}
{"action":{"alias":{"address":"N\u0000sourcecred\u0000discord\u0000MEMBER\u0000user\u0000283112394618568704\u0000","description":"discord/ceresstation#2350"},"identityId":"rrold5b97B5Ka6b2196BRw","type":"ADD_ALIAS"},"ledgerTimestamp":1675041002857,"uuid":"YGJ4j58s2RGNXXlCrENb1w","version":"1"}
{"action":{"identity":{"address":"N\u0000sourcecred\u0000core\u0000IDENTITY\u0000WV7JKfzetZU6dOnlnur9bA\u0000","aliases":[],"id":"WV7JKfzetZU6dOnlnur9bA","name":"Jess-Sloss","subtype":"USER"},"type":"CREATE_IDENTITY"},"ledgerTimestamp":1675041002857,"uuid":"vqkBpXUr6frOuymD9jNoZw","version":"1"}
{"action":{"alias":{"address":"N\u0000sourcecred\u0000discord\u0000MEMBER\u0000user\u0000294610483208519680\u0000","description":"discord/Jess Sloss#6464"},"identityId":"WV7JKfzetZU6dOnlnur9bA","type":"ADD_ALIAS"},"ledgerTimestamp":1675041002857,"uuid":"RRq75U40nPbH9MyULbbylg","version":"1"}
{"action":{"identity":{"address":"N\u0000sourcecred\u0000core\u0000IDENTITY\u0000zBp6B1SZLPAEFjKw5pexZA\u0000","aliases":[],"id":"zBp6B1SZLPAEFjKw5pexZA","name":"Poll-Bot","subtype":"BOT"},"type":"CREATE_IDENTITY"},"ledgerTimestamp":1675041002858,"uuid":"MNCWfDPXQ20T4otOEkbedQ","version":"1"}
{"action":{"alias":{"address":"N\u0000sourcecred\u0000discord\u0000MEMBER\u0000bot\u0000298673420181438465\u0000","description":"discord/Poll Bot#0082"},"identityId":"zBp6B1SZLPAEFjKw5pexZA","type":"ADD_ALIAS"},"ledgerTimestamp":1675041002858,"uuid":"974OpAfGfj8sAcXtYJae4g","version":"1"}
{"action":{"identity":{"address":"N\u0000sourcecred\u0000core\u0000IDENTITY\u0000G6GEk3jTydlAeRhgI8ZDGw\u0000","aliases":[],"id":"G6GEk3jTydlAeRhgI8ZDGw","name":"Micka","subtype":"USER"},"type":"CREATE_IDENTITY"},"ledgerTimestamp":1675041002858,"uuid":"Exx0z9KMrnJtGTBnj679cA","version":"1"}
{"action":{"alias":{"address":"N\u0000sourcecred\u0000discord\u0000MEMBER\u0000user\u0000307626873783844866\u0000","description":"discord/Micka#0144"},"identityId":"G6GEk3jTydlAeRhgI8ZDGw","type":"ADD_ALIAS"},"ledgerTimestamp":1675041002858,"uuid":"dJy3BJCmk7hnKK3A872eJw","version":"1"}
{"action":{"identity":{"address":"N\u0000sourcecred\u0000core\u0000IDENTITY\u0000JqGkm1MA8WdZgDbf5rPzRA\u0000","aliases":[],"id":"JqGkm1MA8WdZgDbf5rPzRA","name":"nh2","subtype":"USER"},"type":"CREATE_IDENTITY"},"ledgerTimestamp":1675041002858,"uuid":"BgN2NKGwMxN0FbvXAHd5Cg","version":"1"}
{"action":{"alias":{"address":"N\u0000sourcecred\u0000discord\u0000MEMBER\u0000user\u0000322650720702562306\u0000","description":"discord/nh2#9555"},"identityId":"JqGkm1MA8WdZgDbf5rPzRA","type":"ADD_ALIAS"},"ledgerTimestamp":1675041002858,"uuid":"UEB0Iod3uVN7Y6ynn8WyqA","version":"1"}
{"action":{"identity":{"address":"N\u0000sourcecred\u0000core\u0000IDENTITY\u0000sJIKocxb2rD74ePM2mvkqQ\u0000","aliases":[],"id":"sJIKocxb2rD74ePM2mvkqQ","name":"SergeiC---ChaDAO","subtype":"USER"},"type":"CREATE_IDENTITY"},"ledgerTimestamp":1675041002858,"uuid":"T8g1ryk3wR9DlCq9Jgps5A","version":"1"}
{"action":{"alias":{"address":"N\u0000sourcecred\u0000discord\u0000MEMBER\u0000user\u0000324583818235478016\u0000","description":"discord/SergeiC | ChaDAO#8795"},"identityId":"sJIKocxb2rD74ePM2mvkqQ","type":"ADD_ALIAS"},"ledgerTimestamp":1675041002858,"uuid":"IGfW7Ijvkz98w0qKQkcxTQ","version":"1"}
{"action":{"identity":{"address":"N\u0000sourcecred\u0000core\u0000IDENTITY\u0000ziDdiRsPlPgX1h9w65dABA\u0000","aliases":[],"id":"ziDdiRsPlPgX1h9w65dABA","name":"Bohdan","subtype":"USER"},"type":"CREATE_IDENTITY"},"ledgerTimestamp":1675041002859,"uuid":"MPDNa0MiNS2B9gMEU1rNkw","version":"1"}
{"action":{"alias":{"address":"N\u0000sourcecred\u0000discord\u0000MEMBER\u0000user\u0000331132795827257344\u0000","description":"discord/Bohdan#3120"},"identityId":"ziDdiRsPlPgX1h9w65dABA","type":"ADD_ALIAS"},"ledgerTimestamp":1675041002859,"uuid":"ArL2udEX0rB5joxL6ytlDg","version":"1"}
{"action":{"identity":{"address":"N\u0000sourcecred\u0000core\u0000IDENTITY\u0000JZfxHOt0CAX8qXxbuwnyvQ\u0000","aliases":[],"id":"JZfxHOt0CAX8qXxbuwnyvQ","name":"scott-L","subtype":"USER"},"type":"CREATE_IDENTITY"},"ledgerTimestamp":1675041002859,"uuid":"9T0cnQJ0rr1EvC5e90Nuaw","version":"1"}
{"action":{"alias":{"address":"N\u0000sourcecred\u0000discord\u0000MEMBER\u0000user\u0000331565457448501258\u0000","description":"discord/scott_L#2131"},"identityId":"JZfxHOt0CAX8qXxbuwnyvQ","type":"ADD_ALIAS"},"ledgerTimestamp":1675041002859,"uuid":"Qy3hlZ1ri3Ercz2Ik6atpA","version":"1"}
{"action":{"identity":{"address":"N\u0000sourcecred\u0000core\u0000IDENTITY\u0000JRMj0wLVN6V83Uogg0JZ0g\u0000","aliases":[],"id":"JRMj0wLVN6V83Uogg0JZ0g","name":"imrankhan","subtype":"USER"},"type":"CREATE_IDENTITY"},"ledgerTimestamp":1675041002860,"uuid":"kYLbU02G51Rij76kA24Heg","version":"1"}
{"action":{"alias":{"address":"N\u0000sourcecred\u0000discord\u0000MEMBER\u0000user\u0000332938903269146625\u0000","description":"discord/imrankhan#9097"},"identityId":"JRMj0wLVN6V83Uogg0JZ0g","type":"ADD_ALIAS"},"ledgerTimestamp":1675041002860,"uuid":"c9ABX7KD29fl4GpoFRlasw","version":"1"}
{"action":{"identity":{"address":"N\u0000sourcecred\u0000core\u0000IDENTITY\u0000pvKAtnb6nnFodFaUAcYKTg\u0000","aliases":[],"id":"pvKAtnb6nnFodFaUAcYKTg","name":"georgi---Nalu","subtype":"USER"},"type":"CREATE_IDENTITY"},"ledgerTimestamp":1675041002860,"uuid":"yM9yBRQB3NU1XvGWnQ3NTA","version":"1"}
{"action":{"alias":{"address":"N\u0000sourcecred\u0000discord\u0000MEMBER\u0000user\u0000335845844555399168\u0000","description":"discord/georgi | Nalu#3430"},"identityId":"pvKAtnb6nnFodFaUAcYKTg","type":"ADD_ALIAS"},"ledgerTimestamp":1675041002860,"uuid":"qTYf4hxo7zkFvtD1d0FpMw","version":"1"}
{"action":{"identity":{"address":"N\u0000sourcecred\u0000core\u0000IDENTITY\u00008BD5njfKw5c2CEZo7HGBIQ\u0000","aliases":[],"id":"8BD5njfKw5c2CEZo7HGBIQ","name":"adrianleb","subtype":"USER"},"type":"CREATE_IDENTITY"},"ledgerTimestamp":1675041002860,"uuid":"fVnWDfyjce4WQwOwa5MMdw","version":"1"}
{"action":{"alias":{"address":"N\u0000sourcecred\u0000discord\u0000MEMBER\u0000user\u0000345908495184298004\u0000","description":"discord/adrianleb#1618"},"identityId":"8BD5njfKw5c2CEZo7HGBIQ","type":"ADD_ALIAS"},"ledgerTimestamp":1675041002861,"uuid":"TEx01Ef5SrcA2gVP2aWNlA","version":"1"}
{"action":{"identity":{"address":"N\u0000sourcecred\u0000core\u0000IDENTITY\u0000bxQqDWfOvZ72c21OXodDKQ\u0000","aliases":[],"id":"bxQqDWfOvZ72c21OXodDKQ","name":"damir-bandalo","subtype":"USER"},"type":"CREATE_IDENTITY"},"ledgerTimestamp":1675041002861,"uuid":"BMX4sY2jn2zCZP6RFoDtzQ","version":"1"}
{"action":{"alias":{"address":"N\u0000sourcecred\u0000discord\u0000MEMBER\u0000user\u0000348213565171302421\u0000","description":"discord/damir.bandalo#4199"},"identityId":"bxQqDWfOvZ72c21OXodDKQ","type":"ADD_ALIAS"},"ledgerTimestamp":1675041002861,"uuid":"u9JzFv4PY1wNYUj3miaKuA","version":"1"}
{"action":{"identity":{"address":"N\u0000sourcecred\u0000core\u0000IDENTITY\u0000lLxWrEMJBPL1ob3bZ52EKg\u0000","aliases":[],"id":"lLxWrEMJBPL1ob3bZ52EKg","name":"Siddharth","subtype":"USER"},"type":"CREATE_IDENTITY"},"ledgerTimestamp":1675041002861,"uuid":"Kf75GwnR3fGBEdGGvji6cQ","version":"1"}
{"action":{"alias":{"address":"N\u0000sourcecred\u0000discord\u0000MEMBER\u0000user\u0000349255175472545802\u0000","description":"discord/Siddharth#6543"},"identityId":"lLxWrEMJBPL1ob3bZ52EKg","type":"ADD_ALIAS"},"ledgerTimestamp":1675041002861,"uuid":"O9vzlF4fdCmaZJ0DaxT4hw","version":"1"}
{"action":{"identity":{"address":"N\u0000sourcecred\u0000core\u0000IDENTITY\u0000JRol50G4TrCGZKeajinvPg\u0000","aliases":[],"id":"JRol50G4TrCGZKeajinvPg","name":"Cassandra","subtype":"USER"},"type":"CREATE_IDENTITY"},"ledgerTimestamp":1675041002861,"uuid":"DTl7tXy5YC8Qowxw34VmMg","version":"1"}
{"action":{"alias":{"address":"N\u0000sourcecred\u0000discord\u0000MEMBER\u0000user\u0000350213851985477632\u0000","description":"discord/Cassandra#5983"},"identityId":"JRol50G4TrCGZKeajinvPg","type":"ADD_ALIAS"},"ledgerTimestamp":1675041002861,"uuid":"Q05zeYk4HzDw3YIEHZE4bQ","version":"1"}
{"action":{"identity":{"address":"N\u0000sourcecred\u0000core\u0000IDENTITY\u0000rzcRjUOwv0v0Y9S9PYpw5Q\u0000","aliases":[],"id":"rzcRjUOwv0v0Y9S9PYpw5Q","name":"kennyrowe","subtype":"USER"},"type":"CREATE_IDENTITY"},"ledgerTimestamp":1675041002862,"uuid":"dMLdvU03u4IloDgVlLPJNQ","version":"1"}
{"action":{"alias":{"address":"N\u0000sourcecred\u0000discord\u0000MEMBER\u0000user\u0000352185193525673984\u0000","description":"discord/kennyrowe#4914"},"identityId":"rzcRjUOwv0v0Y9S9PYpw5Q","type":"ADD_ALIAS"},"ledgerTimestamp":1675041002862,"uuid":"p4YYkvoBVkbw38611JrKgg","version":"1"}
{"action":{"identity":{"address":"N\u0000sourcecred\u0000core\u0000IDENTITY\u000076rOuVDLkEqSpPL6vY72ng\u0000","aliases":[],"id":"76rOuVDLkEqSpPL6vY72ng","name":"Nodar---DeFrag-fi","subtype":"USER"},"type":"CREATE_IDENTITY"},"ledgerTimestamp":1675041002862,"uuid":"Yq7GWvQ6M9xUx8xC3h5OOQ","version":"1"}
{"action":{"alias":{"address":"N\u0000sourcecred\u0000discord\u0000MEMBER\u0000user\u0000354504681231351819\u0000","description":"discord/Nodar | DeFrag.fi#4548"},"identityId":"76rOuVDLkEqSpPL6vY72ng","type":"ADD_ALIAS"},"ledgerTimestamp":1675041002862,"uuid":"fBPmM1P4IxWHqBqL478eZw","version":"1"}
{"action":{"identity":{"address":"N\u0000sourcecred\u0000core\u0000IDENTITY\u0000D90y8vT9i8tk0Fmm8xeljQ\u0000","aliases":[],"id":"D90y8vT9i8tk0Fmm8xeljQ","name":"Lasse-Clausen","subtype":"USER"},"type":"CREATE_IDENTITY"},"ledgerTimestamp":1675041002863,"uuid":"Ph3uomUNJE7wFODOgVJnRA","version":"1"}
{"action":{"alias":{"address":"N\u0000sourcecred\u0000discord\u0000MEMBER\u0000user\u0000355775143944912898\u0000","description":"discord/Lasse Clausen#6198"},"identityId":"D90y8vT9i8tk0Fmm8xeljQ","type":"ADD_ALIAS"},"ledgerTimestamp":1675041002863,"uuid":"RT0PfQPqXckmHzmlXs4jxA","version":"1"}
{"action":{"identity":{"address":"N\u0000sourcecred\u0000core\u0000IDENTITY\u0000hnf8WtLVWd1qMFWLbsEz6w\u0000","aliases":[],"id":"hnf8WtLVWd1qMFWLbsEz6w","name":"arweave-sam","subtype":"USER"},"type":"CREATE_IDENTITY"},"ledgerTimestamp":1675041002863,"uuid":"rUEOEfZrDO27NzA1ajLNjA","version":"1"}
{"action":{"alias":{"address":"N\u0000sourcecred\u0000discord\u0000MEMBER\u0000user\u0000358042048625901570\u0000","description":"discord/arweave-sam#9630"},"identityId":"hnf8WtLVWd1qMFWLbsEz6w","type":"ADD_ALIAS"},"ledgerTimestamp":1675041002863,"uuid":"VdRGrFpKqfdlN8qQWOIZ3A","version":"1"}
{"action":{"identity":{"address":"N\u0000sourcecred\u0000core\u0000IDENTITY\u0000TJxUEtpy0ZfbjqBtbWB4Ow\u0000","aliases":[],"id":"TJxUEtpy0ZfbjqBtbWB4Ow","name":"christopher","subtype":"USER"},"type":"CREATE_IDENTITY"},"ledgerTimestamp":1675041002864,"uuid":"FRQ9jbdwxv929QE9CxLXrA","version":"1"}
{"action":{"alias":{"address":"N\u0000sourcecred\u0000discord\u0000MEMBER\u0000user\u0000363235222587965441\u0000","description":"discord/christopher#3717"},"identityId":"TJxUEtpy0ZfbjqBtbWB4Ow","type":"ADD_ALIAS"},"ledgerTimestamp":1675041002864,"uuid":"kMBijWMOKyMQ8Yd3PEFq6g","version":"1"}
{"action":{"identity":{"address":"N\u0000sourcecred\u0000core\u0000IDENTITY\u0000D2RVIqsQJ5DpdjeX3vXhPw\u0000","aliases":[],"id":"D2RVIqsQJ5DpdjeX3vXhPw","name":"JesseG","subtype":"USER"},"type":"CREATE_IDENTITY"},"ledgerTimestamp":1675041002864,"uuid":"g2yHLAVw21dzolHXlclb2Q","version":"1"}
{"action":{"alias":{"address":"N\u0000sourcecred\u0000discord\u0000MEMBER\u0000user\u0000364578729134915598\u0000","description":"discord/JesseG#2056"},"identityId":"D2RVIqsQJ5DpdjeX3vXhPw","type":"ADD_ALIAS"},"ledgerTimestamp":1675041002864,"uuid":"8ddfDa62p61GznTPmQETwQ","version":"1"}
{"action":{"identity":{"address":"N\u0000sourcecred\u0000core\u0000IDENTITY\u0000NhknegJBf9x5qyKqIrt2wg\u0000","aliases":[],"id":"NhknegJBf9x5qyKqIrt2wg","name":"Julien---bneiluj","subtype":"USER"},"type":"CREATE_IDENTITY"},"ledgerTimestamp":1675041002864,"uuid":"GWp8ixBHV5nbeDTbdHRj8w","version":"1"}
{"action":{"alias":{"address":"N\u0000sourcecred\u0000discord\u0000MEMBER\u0000user\u0000365089145032409088\u0000","description":"discord/Julien | bneiluj#3003"},"identityId":"NhknegJBf9x5qyKqIrt2wg","type":"ADD_ALIAS"},"ledgerTimestamp":1675041002864,"uuid":"BRmaNHQ9ClnG7ZlFnU1O3Q","version":"1"}
{"action":{"identity":{"address":"N\u0000sourcecred\u0000core\u0000IDENTITY\u0000Q6Mb70ZRJ508ygVpkRHeCg\u0000","aliases":[],"id":"Q6Mb70ZRJ508ygVpkRHeCg","name":"Katia","subtype":"USER"},"type":"CREATE_IDENTITY"},"ledgerTimestamp":1675041002865,"uuid":"qDo9sdwbcXLbx0CD7sDbHw","version":"1"}
{"action":{"alias":{"address":"N\u0000sourcecred\u0000discord\u0000MEMBER\u0000user\u0000365161140084408321\u0000","description":"discord/Katia#8152"},"identityId":"Q6Mb70ZRJ508ygVpkRHeCg","type":"ADD_ALIAS"},"ledgerTimestamp":1675041002865,"uuid":"hAEJZlgkwKEa34W3J22eLg","version":"1"}
{"action":{"identity":{"address":"N\u0000sourcecred\u0000core\u0000IDENTITY\u00000fg0t3o5O41NwOBeFLUYLw\u0000","aliases":[],"id":"0fg0t3o5O41NwOBeFLUYLw","name":"nickev","subtype":"USER"},"type":"CREATE_IDENTITY"},"ledgerTimestamp":1675041002865,"uuid":"BxX67VAP4k37pzgeBZbwEw","version":"1"}
{"action":{"alias":{"address":"N\u0000sourcecred\u0000discord\u0000MEMBER\u0000user\u0000367738434120318976\u0000","description":"discord/nickev#0001"},"identityId":"0fg0t3o5O41NwOBeFLUYLw","type":"ADD_ALIAS"},"ledgerTimestamp":1675041002865,"uuid":"sqVIyEJ0KjgFr4z2TvFVnA","version":"1"}
{"action":{"identity":{"address":"N\u0000sourcecred\u0000core\u0000IDENTITY\u0000mi4DlAdMSY6decbA8djrow\u0000","aliases":[],"id":"mi4DlAdMSY6decbA8djrow","name":"Zapier","subtype":"BOT"},"type":"CREATE_IDENTITY"},"ledgerTimestamp":1675041002865,"uuid":"Wywt9NmALEXHOKVa8VWBIg","version":"1"}
{"action":{"alias":{"address":"N\u0000sourcecred\u0000discord\u0000MEMBER\u0000bot\u0000368105370532577280\u0000","description":"discord/Zapier#0625"},"identityId":"mi4DlAdMSY6decbA8djrow","type":"ADD_ALIAS"},"ledgerTimestamp":1675041002866,"uuid":"zgTmoGPxP3dkkx6M6VpgUg","version":"1"}
{"action":{"identity":{"address":"N\u0000sourcecred\u0000core\u0000IDENTITY\u0000o5BXeIr1IwRqblSjygwrwg\u0000","aliases":[],"id":"o5BXeIr1IwRqblSjygwrwg","name":"Jimbobbins","subtype":"USER"},"type":"CREATE_IDENTITY"},"ledgerTimestamp":1675041002866,"uuid":"PBMuVck56RpIA9UxE7O8ww","version":"1"}
{"action":{"alias":{"address":"N\u0000sourcecred\u0000discord\u0000MEMBER\u0000user\u0000368671950144274436\u0000","description":"discord/Jimbobbins#2707"},"identityId":"o5BXeIr1IwRqblSjygwrwg","type":"ADD_ALIAS"},"ledgerTimestamp":1675041002866,"uuid":"sGGXsMPHb2wrbQ08n6CgSg","version":"1"}
{"action":{"identity":{"address":"N\u0000sourcecred\u0000core\u0000IDENTITY\u0000oRO3Or3rfoUx3Ru3RmtajQ\u0000","aliases":[],"id":"oRO3Or3rfoUx3Ru3RmtajQ","name":"insider0x---Rarible","subtype":"USER"},"type":"CREATE_IDENTITY"},"ledgerTimestamp":1675041002866,"uuid":"ZTZI0jlcYznwpm7gCExCPQ","version":"1"}
{"action":{"alias":{"address":"N\u0000sourcecred\u0000discord\u0000MEMBER\u0000user\u0000370298375683178516\u0000","description":"discord/insider0x | Rarible#6638"},"identityId":"oRO3Or3rfoUx3Ru3RmtajQ","type":"ADD_ALIAS"},"ledgerTimestamp":1675041002866,"uuid":"hriJVD7KMgymIvLSx0o8sg","version":"1"}
{"action":{"identity":{"address":"N\u0000sourcecred\u0000core\u0000IDENTITY\u00003bOXhEPYr4Y4kYrpwMxhkA\u0000","aliases":[],"id":"3bOXhEPYr4Y4kYrpwMxhkA","name":"Mark-Lurie---Shipyard","subtype":"USER"},"type":"CREATE_IDENTITY"},"ledgerTimestamp":1675041002866,"uuid":"308VYioAmPBov2uxeElrkQ","version":"1"}
{"action":{"alias":{"address":"N\u0000sourcecred\u0000discord\u0000MEMBER\u0000user\u0000371703044221698059\u0000","description":"discord/Mark Lurie | Shipyard#0001"},"identityId":"3bOXhEPYr4Y4kYrpwMxhkA","type":"ADD_ALIAS"},"ledgerTimestamp":1675041002866,"uuid":"Xytdfexeru53ldcZOeFaOw","version":"1"}
{"action":{"identity":{"address":"N\u0000sourcecred\u0000core\u0000IDENTITY\u0000khlUwodX2TjSPNgKBIjgSw\u0000","aliases":[],"id":"khlUwodX2TjSPNgKBIjgSw","name":"Rolf","subtype":"USER"},"type":"CREATE_IDENTITY"},"ledgerTimestamp":1675041002867,"uuid":"fzCkNBT7WpYug6sKxpN6xQ","version":"1"}
{"action":{"alias":{"address":"N\u0000sourcecred\u0000discord\u0000MEMBER\u0000user\u0000374528909976535040\u0000","description":"discord/Rolf#0664"},"identityId":"khlUwodX2TjSPNgKBIjgSw","type":"ADD_ALIAS"},"ledgerTimestamp":1675041002867,"uuid":"62N3IOrzX7lekWO39Iy6gg","version":"1"}
{"action":{"identity":{"address":"N\u0000sourcecred\u0000core\u0000IDENTITY\u0000GuN2rBEIEy0S5AJhKuVPAg\u0000","aliases":[],"id":"GuN2rBEIEy0S5AJhKuVPAg","name":"Stefan-----","subtype":"USER"},"type":"CREATE_IDENTITY"},"ledgerTimestamp":1675041002867,"uuid":"0F4bOmSP5nd0EtWTevbmkg","version":"1"}
{"action":{"alias":{"address":"N\u0000sourcecred\u0000discord\u0000MEMBER\u0000user\u0000380138695950336001\u0000","description":"discord/Stefan &#x1F5FF;&#x1F30C;#9376"},"identityId":"GuN2rBEIEy0S5AJhKuVPAg","type":"ADD_ALIAS"},"ledgerTimestamp":1675041002867,"uuid":"3K4flNEtYZjdg3fjfohr9A","version":"1"}
{"action":{"identity":{"address":"N\u0000sourcecred\u0000core\u0000IDENTITY\u0000NwKWASVg30L3iRWkVvZQDA\u0000","aliases":[],"id":"NwKWASVg30L3iRWkVvZQDA","name":"raf","subtype":"USER"},"type":"CREATE_IDENTITY"},"ledgerTimestamp":1675041002868,"uuid":"hRMRRj2AC1eO7p7xAxQTlw","version":"1"}
{"action":{"alias":{"address":"N\u0000sourcecred\u0000discord\u0000MEMBER\u0000user\u0000381907024910221323\u0000","description":"discord/raf#7028"},"identityId":"NwKWASVg30L3iRWkVvZQDA","type":"ADD_ALIAS"},"ledgerTimestamp":1675041002868,"uuid":"6hPDhNrOOKKx0FO876RYoA","version":"1"}
{"action":{"identity":{"address":"N\u0000sourcecred\u0000core\u0000IDENTITY\u00002Eta0IzRg7dkp0Wukdve3w\u0000","aliases":[],"id":"2Eta0IzRg7dkp0Wukdve3w","name":"jesse","subtype":"USER"},"type":"CREATE_IDENTITY"},"ledgerTimestamp":1675041002868,"uuid":"mYZ9lupKSRblrlWSrD9Teg","version":"1"}
{"action":{"alias":{"address":"N\u0000sourcecred\u0000discord\u0000MEMBER\u0000user\u0000382663515552481301\u0000","description":"discord/jesse#0351"},"identityId":"2Eta0IzRg7dkp0Wukdve3w","type":"ADD_ALIAS"},"ledgerTimestamp":1675041002868,"uuid":"qZXIwwV1Desd0t0Axp6bLA","version":"1"}
{"action":{"identity":{"address":"N\u0000sourcecred\u0000core\u0000IDENTITY\u0000eRt701rDi4qOqSgnHnCAjQ\u0000","aliases":[],"id":"eRt701rDi4qOqSgnHnCAjQ","name":"Stefan","subtype":"USER"},"type":"CREATE_IDENTITY"},"ledgerTimestamp":1675041002868,"uuid":"EeCYWp8Vq3x5Lg28WWlvSA","version":"1"}
{"action":{"alias":{"address":"N\u0000sourcecred\u0000discord\u0000MEMBER\u0000user\u0000382678030503510027\u0000","description":"discord/Stefan#7488"},"identityId":"eRt701rDi4qOqSgnHnCAjQ","type":"ADD_ALIAS"},"ledgerTimestamp":1675041002868,"uuid":"7WLc2a1b5AEMZ0PTLBSWwg","version":"1"}
{"action":{"identity":{"address":"N\u0000sourcecred\u0000core\u0000IDENTITY\u0000jbhbe8rdrQUDr2N0y1Tm7g\u0000","aliases":[],"id":"jbhbe8rdrQUDr2N0y1Tm7g","name":"dre---RAC","subtype":"USER"},"type":"CREATE_IDENTITY"},"ledgerTimestamp":1675041002868,"uuid":"ZxbEdwpE0djBXFbahpL5uQ","version":"1"}
{"action":{"alias":{"address":"N\u0000sourcecred\u0000discord\u0000MEMBER\u0000user\u0000385259050226679811\u0000","description":"discord/dre &#x25B3; RAC#7262"},"identityId":"jbhbe8rdrQUDr2N0y1Tm7g","type":"ADD_ALIAS"},"ledgerTimestamp":1675041002868,"uuid":"wQCQ0Xro4EK4ZiqXobx4IQ","version":"1"}
{"action":{"identity":{"address":"N\u0000sourcecred\u0000core\u0000IDENTITY\u0000qDgKb1ZgSatmjLSxT1SGDA\u0000","aliases":[],"id":"qDgKb1ZgSatmjLSxT1SGDA","name":"Jihoz","subtype":"USER"},"type":"CREATE_IDENTITY"},"ledgerTimestamp":1675041002868,"uuid":"LnJ9y17bvdDpek7JWWE5JA","version":"1"}
{"action":{"alias":{"address":"N\u0000sourcecred\u0000discord\u0000MEMBER\u0000user\u0000386948687525576704\u0000","description":"discord/Jihoz#5202"},"identityId":"qDgKb1ZgSatmjLSxT1SGDA","type":"ADD_ALIAS"},"ledgerTimestamp":1675041002868,"uuid":"9vu8zP9CwXqI2JbOMce0eQ","version":"1"}
{"action":{"identity":{"address":"N\u0000sourcecred\u0000core\u0000IDENTITY\u0000dldwAgwbBpWn3O3BRxTYBA\u0000","aliases":[],"id":"dldwAgwbBpWn3O3BRxTYBA","name":"johan---meme-com","subtype":"USER"},"type":"CREATE_IDENTITY"},"ledgerTimestamp":1675041002869,"uuid":"b4t7ipZN99LGcY7DgoMQkg","version":"1"}
{"action":{"alias":{"address":"N\u0000sourcecred\u0000discord\u0000MEMBER\u0000user\u0000387714655331680259\u0000","description":"discord/johan | meme.com#2764"},"identityId":"dldwAgwbBpWn3O3BRxTYBA","type":"ADD_ALIAS"},"ledgerTimestamp":1675041002869,"uuid":"PHWfXt6GWj0qwQWilKxUqw","version":"1"}
{"action":{"identity":{"address":"N\u0000sourcecred\u0000core\u0000IDENTITY\u0000Q0bBxge0anbG5sNI3RxAlg\u0000","aliases":[],"id":"Q0bBxge0anbG5sNI3RxAlg","name":"Fran---Superfluid","subtype":"USER"},"type":"CREATE_IDENTITY"},"ledgerTimestamp":1675041002869,"uuid":"AsL0jdnPeWtR9kbjQPFZBw","version":"1"}
{"action":{"alias":{"address":"N\u0000sourcecred\u0000discord\u0000MEMBER\u0000user\u0000388117002448928783\u0000","description":"discord/Fran | Superfluid#1792"},"identityId":"Q0bBxge0anbG5sNI3RxAlg","type":"ADD_ALIAS"},"ledgerTimestamp":1675041002869,"uuid":"jsbb3iEzyldBrkYahgfazQ","version":"1"}
{"action":{"identity":{"address":"N\u0000sourcecred\u0000core\u0000IDENTITY\u0000uqgvY53CXQfPrYgM16pBGg\u0000","aliases":[],"id":"uqgvY53CXQfPrYgM16pBGg","name":"jns","subtype":"USER"},"type":"CREATE_IDENTITY"},"ledgerTimestamp":1675041002869,"uuid":"5JEGBSpkr4WyNe199YapDQ","version":"1"}
{"action":{"alias":{"address":"N\u0000sourcecred\u0000discord\u0000MEMBER\u0000user\u0000388851131339636741\u0000","description":"discord/jns#1594"},"identityId":"uqgvY53CXQfPrYgM16pBGg","type":"ADD_ALIAS"},"ledgerTimestamp":1675041002869,"uuid":"aDmn3sr2HKzMZwEXleim3Q","version":"1"}
{"action":{"identity":{"address":"N\u0000sourcecred\u0000core\u0000IDENTITY\u0000dDycLBRlx8nXBMDeBDRvDQ\u0000","aliases":[],"id":"dDycLBRlx8nXBMDeBDRvDQ","name":"UBIpromoter--","subtype":"USER"},"type":"CREATE_IDENTITY"},"ledgerTimestamp":1675041002869,"uuid":"T3MEauoA2Fp2fjt46mvmbw","version":"1"}
{"action":{"alias":{"address":"N\u0000sourcecred\u0000discord\u0000MEMBER\u0000user\u0000391253771843403790\u0000","description":"discord/UBIpromoter&#x1F506;#4402"},"identityId":"dDycLBRlx8nXBMDeBDRvDQ","type":"ADD_ALIAS"},"ledgerTimestamp":1675041002869,"uuid":"uXeIMFkOZ5fk5Zp8odRWAw","version":"1"}
{"action":{"identity":{"address":"N\u0000sourcecred\u0000core\u0000IDENTITY\u0000IW8u75YE3MP4j6tbPHxjOw\u0000","aliases":[],"id":"IW8u75YE3MP4j6tbPHxjOw","name":"cruz","subtype":"USER"},"type":"CREATE_IDENTITY"},"ledgerTimestamp":1675041002870,"uuid":"ieTve3yFlr4DEA1cBf7ziQ","version":"1"}
{"action":{"alias":{"address":"N\u0000sourcecred\u0000discord\u0000MEMBER\u0000user\u0000397450277365612555\u0000","description":"discord/cruz#5418"},"identityId":"IW8u75YE3MP4j6tbPHxjOw","type":"ADD_ALIAS"},"ledgerTimestamp":1675041002870,"uuid":"v3PeQX92gKelA7neJdWBsQ","version":"1"}
{"action":{"identity":{"address":"N\u0000sourcecred\u0000core\u0000IDENTITY\u0000D9AVb0RxpFA2PDCRaB49pg\u0000","aliases":[],"id":"D9AVb0RxpFA2PDCRaB49pg","name":"hilmarx","subtype":"USER"},"type":"CREATE_IDENTITY"},"ledgerTimestamp":1675041002870,"uuid":"JQta2IZePESyWp41G5xQ7A","version":"1"}
{"action":{"alias":{"address":"N\u0000sourcecred\u0000discord\u0000MEMBER\u0000user\u0000397944363704909826\u0000","description":"discord/hilmarx#1412"},"identityId":"D9AVb0RxpFA2PDCRaB49pg","type":"ADD_ALIAS"},"ledgerTimestamp":1675041002870,"uuid":"JDyIDq8FXLSBaDtQ7bmXjA","version":"1"}
{"action":{"identity":{"address":"N\u0000sourcecred\u0000core\u0000IDENTITY\u0000f0rTMq9LkDtMvWLBmKOuBw\u0000","aliases":[],"id":"f0rTMq9LkDtMvWLBmKOuBw","name":"Rex","subtype":"USER"},"type":"CREATE_IDENTITY"},"ledgerTimestamp":1675041002871,"uuid":"jkuaj6nAIkRFOlvi8LfDAQ","version":"1"}
{"action":{"alias":{"address":"N\u0000sourcecred\u0000discord\u0000MEMBER\u0000user\u0000399384703439863829\u0000","description":"discord/Rex#1134"},"identityId":"f0rTMq9LkDtMvWLBmKOuBw","type":"ADD_ALIAS"},"ledgerTimestamp":1675041002871,"uuid":"HEQx19exo8O4fxmdx03OiQ","version":"1"}
{"action":{"identity":{"address":"N\u0000sourcecred\u0000core\u0000IDENTITY\u0000QtJrEQyOBEjqvkrL0OJmCA\u0000","aliases":[],"id":"QtJrEQyOBEjqvkrL0OJmCA","name":"IgorA","subtype":"USER"},"type":"CREATE_IDENTITY"},"ledgerTimestamp":1675041002871,"uuid":"qNfPJhkheVobkn5KBI5Jdg","version":"1"}
{"action":{"alias":{"address":"N\u0000sourcecred\u0000discord\u0000MEMBER\u0000user\u0000402432563634765826\u0000","description":"discord/IgorA#8902"},"identityId":"QtJrEQyOBEjqvkrL0OJmCA","type":"ADD_ALIAS"},"ledgerTimestamp":1675041002871,"uuid":"erTQWODOIWaUW7XIEsgeMw","version":"1"}
{"action":{"identity":{"address":"N\u0000sourcecred\u0000core\u0000IDENTITY\u00004QyBesZAjq4lSLrcbZkHeg\u0000","aliases":[],"id":"4QyBesZAjq4lSLrcbZkHeg","name":"cjliu49","subtype":"USER"},"type":"CREATE_IDENTITY"},"ledgerTimestamp":1675041002871,"uuid":"r7AzRfKW44ryoBoLph3Wfg","version":"1"}
{"action":{"alias":{"address":"N\u0000sourcecred\u0000discord\u0000MEMBER\u0000user\u0000407624488444755978\u0000","description":"discord/cjliu49#4835"},"identityId":"4QyBesZAjq4lSLrcbZkHeg","type":"ADD_ALIAS"},"ledgerTimestamp":1675041002871,"uuid":"bbBN5yMCbfobEACxoCDJ9A","version":"1"}
{"action":{"identity":{"address":"N\u0000sourcecred\u0000core\u0000IDENTITY\u0000Wa6mj4d6w3VhGbFERug4ag\u0000","aliases":[],"id":"Wa6mj4d6w3VhGbFERug4ag","name":"Eth2Moon","subtype":"USER"},"type":"CREATE_IDENTITY"},"ledgerTimestamp":1675041002871,"uuid":"dul0lBX9soAAhNhbxH0SbA","version":"1"}
{"action":{"alias":{"address":"N\u0000sourcecred\u0000discord\u0000MEMBER\u0000user\u0000409929236116275212\u0000","description":"discord/Eth2Moon#8918"},"identityId":"Wa6mj4d6w3VhGbFERug4ag","type":"ADD_ALIAS"},"ledgerTimestamp":1675041002871,"uuid":"rKiZc05bcdjWjnDKUa6cWA","version":"1"}
{"action":{"identity":{"address":"N\u0000sourcecred\u0000core\u0000IDENTITY\u0000rcBdFWDG3SjtZLUR20SytA\u0000","aliases":[],"id":"rcBdFWDG3SjtZLUR20SytA","name":"See-Eun-Ha","subtype":"USER"},"type":"CREATE_IDENTITY"},"ledgerTimestamp":1675041002871,"uuid":"Am126qYMSpXe85OomvB3eg","version":"1"}
{"action":{"alias":{"address":"N\u0000sourcecred\u0000discord\u0000MEMBER\u0000user\u0000410426981260197890\u0000","description":"discord/See Eun Ha#8577"},"identityId":"rcBdFWDG3SjtZLUR20SytA","type":"ADD_ALIAS"},"ledgerTimestamp":1675041002871,"uuid":"L6whbcaxlmJOYZI08KpRJQ","version":"1"}
{"action":{"identity":{"address":"N\u0000sourcecred\u0000core\u0000IDENTITY\u00002lrDpfwQE4gVHx8ZypH2tg\u0000","aliases":[],"id":"2lrDpfwQE4gVHx8ZypH2tg","name":"Bobby-Ong","subtype":"USER"},"type":"CREATE_IDENTITY"},"ledgerTimestamp":1675041002872,"uuid":"72VnbviBfpGPywD0cJKjIw","version":"1"}
{"action":{"alias":{"address":"N\u0000sourcecred\u0000discord\u0000MEMBER\u0000user\u0000411441465340723200\u0000","description":"discord/Bobby Ong#1087"},"identityId":"2lrDpfwQE4gVHx8ZypH2tg","type":"ADD_ALIAS"},"ledgerTimestamp":1675041002872,"uuid":"JTpVbZGlFMs14B3kMFwQIQ","version":"1"}
{"action":{"identity":{"address":"N\u0000sourcecred\u0000core\u0000IDENTITY\u0000TEZkhebwnKBf4BGK66WiPA\u0000","aliases":[],"id":"TEZkhebwnKBf4BGK66WiPA","name":"Kubo-G---HydraDX-io","subtype":"USER"},"type":"CREATE_IDENTITY"},"ledgerTimestamp":1675041002872,"uuid":"Br9WvQbz5HXARnVkuZyg9A","version":"1"}
{"action":{"alias":{"address":"N\u0000sourcecred\u0000discord\u0000MEMBER\u0000user\u0000411895119646687233\u0000","description":"discord/Kubo.G | HydraDX.io#9080"},"identityId":"TEZkhebwnKBf4BGK66WiPA","type":"ADD_ALIAS"},"ledgerTimestamp":1675041002872,"uuid":"ZnF9AS42wRYJR2OYWQYBeQ","version":"1"}
{"action":{"identity":{"address":"N\u0000sourcecred\u0000core\u0000IDENTITY\u0000NKMXmRAMWmNGReXT2mwdRQ\u0000","aliases":[],"id":"NKMXmRAMWmNGReXT2mwdRQ","name":"worthalter---POAP","subtype":"USER"},"type":"CREATE_IDENTITY"},"ledgerTimestamp":1675041002872,"uuid":"4ZGEDXiXI17QLiL7dsP9Xg","version":"1"}
{"action":{"alias":{"address":"N\u0000sourcecred\u0000discord\u0000MEMBER\u0000user\u0000411952680244740096\u0000","description":"discord/worthalter | POAP#0001"},"identityId":"NKMXmRAMWmNGReXT2mwdRQ","type":"ADD_ALIAS"},"ledgerTimestamp":1675041002872,"uuid":"SMVaf5rf3t2DZFB45nNwHQ","version":"1"}
{"action":{"identity":{"address":"N\u0000sourcecred\u0000core\u0000IDENTITY\u0000lr5cjKeh9vc2Lmx9psxhqQ\u0000","aliases":[],"id":"lr5cjKeh9vc2Lmx9psxhqQ","name":"benchan","subtype":"USER"},"type":"CREATE_IDENTITY"},"ledgerTimestamp":1675041002873,"uuid":"BbXx4b6Pg6vkdPVmU5KiWA","version":"1"}
{"action":{"alias":{"address":"N\u0000sourcecred\u0000discord\u0000MEMBER\u0000user\u0000412472821663531020\u0000","description":"discord/benchan#8517"},"identityId":"lr5cjKeh9vc2Lmx9psxhqQ","type":"ADD_ALIAS"},"ledgerTimestamp":1675041002873,"uuid":"mP971DNWkc4t22tdd0tKVQ","version":"1"}
{"action":{"identity":{"address":"N\u0000sourcecred\u0000core\u0000IDENTITY\u0000nuJbD6gMpWPP1YTqA4pVlg\u0000","aliases":[],"id":"nuJbD6gMpWPP1YTqA4pVlg","name":"Pascal-from-the-Netherlands","subtype":"USER"},"type":"CREATE_IDENTITY"},"ledgerTimestamp":1675041002873,"uuid":"Pgz65vpW42BA40ZlwOegtw","version":"1"}
{"action":{"alias":{"address":"N\u0000sourcecred\u0000discord\u0000MEMBER\u0000user\u0000412588510227202050\u0000","description":"discord/Pascal from the Netherlands#3569"},"identityId":"nuJbD6gMpWPP1YTqA4pVlg","type":"ADD_ALIAS"},"ledgerTimestamp":1675041002873,"uuid":"lTZgzXGkDU0ceLfmud4zmQ","version":"1"}
{"action":{"identity":{"address":"N\u0000sourcecred\u0000core\u0000IDENTITY\u0000nUEl3hqd22Jld2PXw6hqjw\u0000","aliases":[],"id":"nUEl3hqd22Jld2PXw6hqjw","name":"o-rourke","subtype":"USER"},"type":"CREATE_IDENTITY"},"ledgerTimestamp":1675041002873,"uuid":"cq7X5J8EwbEevO9oyEmElw","version":"1"}
{"action":{"alias":{"address":"N\u0000sourcecred\u0000discord\u0000MEMBER\u0000user\u0000416318100015677442\u0000","description":"discord/o_rourke#9796"},"identityId":"nUEl3hqd22Jld2PXw6hqjw","type":"ADD_ALIAS"},"ledgerTimestamp":1675041002873,"uuid":"AkyD3VWwo0Jo4m9cNMtAQA","version":"1"}
{"action":{"identity":{"address":"N\u0000sourcecred\u0000core\u0000IDENTITY\u0000irb8wnmWPylUMObUpwG9iw\u0000","aliases":[],"id":"irb8wnmWPylUMObUpwG9iw","name":"BrucePon","subtype":"USER"},"type":"CREATE_IDENTITY"},"ledgerTimestamp":1675041002873,"uuid":"16yjargd7qDPEKWnRPJPRQ","version":"1"}
{"action":{"alias":{"address":"N\u0000sourcecred\u0000discord\u0000MEMBER\u0000user\u0000419839406636269569\u0000","description":"discord/BrucePon#2995"},"identityId":"irb8wnmWPylUMObUpwG9iw","type":"ADD_ALIAS"},"ledgerTimestamp":1675041002873,"uuid":"NSV466WSzOWpfAQl1ULkZQ","version":"1"}
{"action":{"identity":{"address":"N\u0000sourcecred\u0000core\u0000IDENTITY\u0000YOCNrBnqsP9SeMeAbT9DcQ\u0000","aliases":[],"id":"YOCNrBnqsP9SeMeAbT9DcQ","name":"Winslow","subtype":"USER"},"type":"CREATE_IDENTITY"},"ledgerTimestamp":1675041002873,"uuid":"1sEsKZ0oOmnBH5ooTrPk1w","version":"1"}
{"action":{"alias":{"address":"N\u0000sourcecred\u0000discord\u0000MEMBER\u0000user\u0000419903116016877573\u0000","description":"discord/Winslow#0252"},"identityId":"YOCNrBnqsP9SeMeAbT9DcQ","type":"ADD_ALIAS"},"ledgerTimestamp":1675041002874,"uuid":"UembvoYqM7ETz1CQYyg2Ww","version":"1"}
{"action":{"identity":{"address":"N\u0000sourcecred\u0000core\u0000IDENTITY\u0000oyDqLW4rPFqu0MTEPk4IvQ\u0000","aliases":[],"id":"oyDqLW4rPFqu0MTEPk4IvQ","name":"Andrew---Reality-Cards---","subtype":"USER"},"type":"CREATE_IDENTITY"},"ledgerTimestamp":1675041002874,"uuid":"0QlkkUpKl4w3ZqBdDLDHYQ","version":"1"}
{"action":{"alias":{"address":"N\u0000sourcecred\u0000discord\u0000MEMBER\u0000user\u0000420508562846908417\u0000","description":"discord/Andrew | Reality Cards &#x1F3B4;#4617"},"identityId":"oyDqLW4rPFqu0MTEPk4IvQ","type":"ADD_ALIAS"},"ledgerTimestamp":1675041002874,"uuid":"Mpzb5kV53o6wG1mjOGrPfA","version":"1"}
{"action":{"identity":{"address":"N\u0000sourcecred\u0000core\u0000IDENTITY\u0000Kv3gSm699XbdJCkgZMVBkA\u0000","aliases":[],"id":"Kv3gSm699XbdJCkgZMVBkA","name":"Sergio---FLOC-","subtype":"USER"},"type":"CREATE_IDENTITY"},"ledgerTimestamp":1675041002874,"uuid":"ub5Qu0wc7bKUbyVbuvyb4A","version":"1"}
{"action":{"alias":{"address":"N\u0000sourcecred\u0000discord\u0000MEMBER\u0000user\u0000422762837773910017\u0000","description":"discord/Sergio | FLOC*#0013"},"identityId":"Kv3gSm699XbdJCkgZMVBkA","type":"ADD_ALIAS"},"ledgerTimestamp":1675041002874,"uuid":"Et1DcM5OIdBbJzqJrzLcww","version":"1"}
{"action":{"identity":{"address":"N\u0000sourcecred\u0000core\u0000IDENTITY\u000088W5yxRgvWq5qJjmn396AA\u0000","aliases":[],"id":"88W5yxRgvWq5qJjmn396AA","name":"NONFUNGEO","subtype":"USER"},"type":"CREATE_IDENTITY"},"ledgerTimestamp":1675041002874,"uuid":"U7B2JATVxvYjKFKk0pXd0Q","version":"1"}
{"action":{"alias":{"address":"N\u0000sourcecred\u0000discord\u0000MEMBER\u0000user\u0000425012809324298247\u0000","description":"discord/NONFUNGEO#6230"},"identityId":"88W5yxRgvWq5qJjmn396AA","type":"ADD_ALIAS"},"ledgerTimestamp":1675041002874,"uuid":"qUw8dKOVUkYHNdHAU3X9rQ","version":"1"}
{"action":{"identity":{"address":"N\u0000sourcecred\u0000core\u0000IDENTITY\u0000H7EudEI2Bt6dszL9n5LywA\u0000","aliases":[],"id":"H7EudEI2Bt6dszL9n5LywA","name":"dm-bot--send-anon--msg--","subtype":"BOT"},"type":"CREATE_IDENTITY"},"ledgerTimestamp":1675041002875,"uuid":"T5lxxRU4rOn0Zgc6UgYEAA","version":"1"}
{"action":{"alias":{"address":"N\u0000sourcecred\u0000discord\u0000MEMBER\u0000bot\u0000425833927517798420\u0000","description":"discord/dm bot &#x22;send anon [msg]&#x22;#8387"},"identityId":"H7EudEI2Bt6dszL9n5LywA","type":"ADD_ALIAS"},"ledgerTimestamp":1675041002875,"uuid":"2j9yB3QyQPmDN1pszk7YUg","version":"1"}
{"action":{"identity":{"address":"N\u0000sourcecred\u0000core\u0000IDENTITY\u0000tgW1Bfbf3LlbS8wkamQuYg\u0000","aliases":[],"id":"tgW1Bfbf3LlbS8wkamQuYg","name":"keldster","subtype":"USER"},"type":"CREATE_IDENTITY"},"ledgerTimestamp":1675041002875,"uuid":"7ogdPYoOgR8vKo4uEv9Rrw","version":"1"}
{"action":{"alias":{"address":"N\u0000sourcecred\u0000discord\u0000MEMBER\u0000user\u0000435368998230687764\u0000","description":"discord/keldster#6406"},"identityId":"tgW1Bfbf3LlbS8wkamQuYg","type":"ADD_ALIAS"},"ledgerTimestamp":1675041002875,"uuid":"Bfql645SGnQpUKyqappmVg","version":"1"}
{"action":{"identity":{"address":"N\u0000sourcecred\u0000core\u0000IDENTITY\u000093ZbeqEaojdpV50HGljh3w\u0000","aliases":[],"id":"93ZbeqEaojdpV50HGljh3w","name":"Mattias---Meme-com","subtype":"USER"},"type":"CREATE_IDENTITY"},"ledgerTimestamp":1675041002875,"uuid":"4vuMI9mlroG8Ku6Nc3IGsA","version":"1"}
{"action":{"alias":{"address":"N\u0000sourcecred\u0000discord\u0000MEMBER\u0000user\u0000436250445174931456\u0000","description":"discord/Mattias | Meme.com#8984"},"identityId":"93ZbeqEaojdpV50HGljh3w","type":"ADD_ALIAS"},"ledgerTimestamp":1675041002875,"uuid":"klHxjwO1ZzOqjJVV26uQCQ","version":"1"}
{"action":{"identity":{"address":"N\u0000sourcecred\u0000core\u0000IDENTITY\u00000VPm3YaLUxlpXDohgy46yw\u0000","aliases":[],"id":"0VPm3YaLUxlpXDohgy46yw","name":"Regan-Bozman","subtype":"USER"},"type":"CREATE_IDENTITY"},"ledgerTimestamp":1675041002875,"uuid":"Ldz6qPWXA7kdnpKhbdQyew","version":"1"}
{"action":{"alias":{"address":"N\u0000sourcecred\u0000discord\u0000MEMBER\u0000user\u0000440966315075960843\u0000","description":"discord/Regan Bozman#2244"},"identityId":"0VPm3YaLUxlpXDohgy46yw","type":"ADD_ALIAS"},"ledgerTimestamp":1675041002875,"uuid":"8BMbiatM91hnJLE7ghRG9g","version":"1"}
{"action":{"identity":{"address":"N\u0000sourcecred\u0000core\u0000IDENTITY\u0000wqBrAiBjYdIz6W6j7phruw\u0000","aliases":[],"id":"wqBrAiBjYdIz6W6j7phruw","name":"Fiskantes","subtype":"USER"},"type":"CREATE_IDENTITY"},"ledgerTimestamp":1675041002876,"uuid":"WUV1dhx7OBuGmWNpBk0YCA","version":"1"}
{"action":{"alias":{"address":"N\u0000sourcecred\u0000discord\u0000MEMBER\u0000user\u0000442072176779198486\u0000","description":"discord/Fiskantes#6036"},"identityId":"wqBrAiBjYdIz6W6j7phruw","type":"ADD_ALIAS"},"ledgerTimestamp":1675041002876,"uuid":"WJCeVRDfkmIZON65Yl1Jdw","version":"1"}
{"action":{"identity":{"address":"N\u0000sourcecred\u0000core\u0000IDENTITY\u0000pmLIGnJznTdGlgz299O5Yg\u0000","aliases":[],"id":"pmLIGnJznTdGlgz299O5Yg","name":"pet3rpan","subtype":"USER"},"type":"CREATE_IDENTITY"},"ledgerTimestamp":1675041002876,"uuid":"jLt8Gv0rqBGPT8sxWwarUg","version":"1"}
{"action":{"alias":{"address":"N\u0000sourcecred\u0000discord\u0000MEMBER\u0000user\u0000443527705250758696\u0000","description":"discord/pet3rpan#4352"},"identityId":"pmLIGnJznTdGlgz299O5Yg","type":"ADD_ALIAS"},"ledgerTimestamp":1675041002876,"uuid":"NjEJsE220qfdHZAkl4EBCQ","version":"1"}
{"action":{"identity":{"address":"N\u0000sourcecred\u0000core\u0000IDENTITY\u0000NohMg0LDn0l1aD9oY3WksA\u0000","aliases":[],"id":"NohMg0LDn0l1aD9oY3WksA","name":"George-Lambeth","subtype":"USER"},"type":"CREATE_IDENTITY"},"ledgerTimestamp":1675041002876,"uuid":"8SbBMR21Arip9XvZNP3sPA","version":"1"}
{"action":{"alias":{"address":"N\u0000sourcecred\u0000discord\u0000MEMBER\u0000user\u0000445606223539339274\u0000","description":"discord/George Lambeth#2835"},"identityId":"NohMg0LDn0l1aD9oY3WksA","type":"ADD_ALIAS"},"ledgerTimestamp":1675041002876,"uuid":"Cnrzndz4PJkU4Zfa9J2jkw","version":"1"}
{"action":{"identity":{"address":"N\u0000sourcecred\u0000core\u0000IDENTITY\u0000RpmPM7L1RrPatK3PMd15sg\u0000","aliases":[],"id":"RpmPM7L1RrPatK3PMd15sg","name":"Graham","subtype":"USER"},"type":"CREATE_IDENTITY"},"ledgerTimestamp":1675041002876,"uuid":"QKfoNpyTd7qpAREmlIkCoA","version":"1"}
{"action":{"alias":{"address":"N\u0000sourcecred\u0000discord\u0000MEMBER\u0000user\u0000453601646832910346\u0000","description":"discord/Graham#2996"},"identityId":"RpmPM7L1RrPatK3PMd15sg","type":"ADD_ALIAS"},"ledgerTimestamp":1675041002877,"uuid":"3G5xxpjrb8ohkL6oC0ANmw","version":"1"}
{"action":{"identity":{"address":"N\u0000sourcecred\u0000core\u0000IDENTITY\u0000Li1qrYVgM4cmraaGlupz1w\u0000","aliases":[],"id":"Li1qrYVgM4cmraaGlupz1w","name":"0x-vadym---ChaDAO","subtype":"USER"},"type":"CREATE_IDENTITY"},"ledgerTimestamp":1675041002877,"uuid":"teOTgZprvEDq0ySl596m7Q","version":"1"}
{"action":{"alias":{"address":"N\u0000sourcecred\u0000discord\u0000MEMBER\u0000user\u0000454250406491717642\u0000","description":"discord/0x_vadym | ChaDAO#8908"},"identityId":"Li1qrYVgM4cmraaGlupz1w","type":"ADD_ALIAS"},"ledgerTimestamp":1675041002877,"uuid":"j9unRZ5x27ILS5DSPVWL9w","version":"1"}
{"action":{"identity":{"address":"N\u0000sourcecred\u0000core\u0000IDENTITY\u0000uoOrImiMklmtbr4PBDU0YA\u0000","aliases":[],"id":"uoOrImiMklmtbr4PBDU0YA","name":"EricArsenault","subtype":"USER"},"type":"CREATE_IDENTITY"},"ledgerTimestamp":1675041002877,"uuid":"gpWKOH6qPzZFoA9BRALV5w","version":"1"}
{"action":{"alias":{"address":"N\u0000sourcecred\u0000discord\u0000MEMBER\u0000user\u0000459085466239631371\u0000","description":"discord/EricArsenault#4072"},"identityId":"uoOrImiMklmtbr4PBDU0YA","type":"ADD_ALIAS"},"ledgerTimestamp":1675041002877,"uuid":"fAUk6vvMI0pmKme1dr3BjQ","version":"1"}
{"action":{"identity":{"address":"N\u0000sourcecred\u0000core\u0000IDENTITY\u0000Ae6VlK1o3jUOZHwC6bu5zQ\u0000","aliases":[],"id":"Ae6VlK1o3jUOZHwC6bu5zQ","name":"chadwick","subtype":"USER"},"type":"CREATE_IDENTITY"},"ledgerTimestamp":1675041002878,"uuid":"coJhEtYqhn6QHVorKFy9IQ","version":"1"}
{"action":{"alias":{"address":"N\u0000sourcecred\u0000discord\u0000MEMBER\u0000user\u0000461278596602920961\u0000","description":"discord/chadwick#5132"},"identityId":"Ae6VlK1o3jUOZHwC6bu5zQ","type":"ADD_ALIAS"},"ledgerTimestamp":1675041002878,"uuid":"W9WgUDar9g580CQKRcoePA","version":"1"}
{"action":{"identity":{"address":"N\u0000sourcecred\u0000core\u0000IDENTITY\u0000gU5u8f9jtgq28c44hnTv8A\u0000","aliases":[],"id":"gU5u8f9jtgq28c44hnTv8A","name":"Ali---opium-team","subtype":"USER"},"type":"CREATE_IDENTITY"},"ledgerTimestamp":1675041002878,"uuid":"MWienLq7Cqh3KBobI8WaXg","version":"1"}
{"action":{"alias":{"address":"N\u0000sourcecred\u0000discord\u0000MEMBER\u0000user\u0000463100417924923402\u0000","description":"discord/Ali | opium.team#0384"},"identityId":"gU5u8f9jtgq28c44hnTv8A","type":"ADD_ALIAS"},"ledgerTimestamp":1675041002878,"uuid":"IyS7XIwM5HWt4XZWAkXcXQ","version":"1"}
{"action":{"identity":{"address":"N\u0000sourcecred\u0000core\u0000IDENTITY\u00002nnLJtEG0getzZTr345ytw\u0000","aliases":[],"id":"2nnLJtEG0getzZTr345ytw","name":"mikey-rf","subtype":"USER"},"type":"CREATE_IDENTITY"},"ledgerTimestamp":1675041002878,"uuid":"Gt8mAndBY5nJ04T9aMW3Bg","version":"1"}
{"action":{"alias":{"address":"N\u0000sourcecred\u0000discord\u0000MEMBER\u0000user\u0000473245575991787530\u0000","description":"discord/mikey.rf#0121"},"identityId":"2nnLJtEG0getzZTr345ytw","type":"ADD_ALIAS"},"ledgerTimestamp":1675041002878,"uuid":"7UwJAx57W0h3RGdRb5Ax1Q","version":"1"}
{"action":{"identity":{"address":"N\u0000sourcecred\u0000core\u0000IDENTITY\u0000mkh8LXgOgbEdI8aMaQLFDA\u0000","aliases":[],"id":"mkh8LXgOgbEdI8aMaQLFDA","name":"-xmwu","subtype":"USER"},"type":"CREATE_IDENTITY"},"ledgerTimestamp":1675041002878,"uuid":"gvUWgVq8sErXrOXQ1bjWZw","version":"1"}
{"action":{"alias":{"address":"N\u0000sourcecred\u0000discord\u0000MEMBER\u0000user\u0000474564362674241536\u0000","description":"discord/-xmwu#8083"},"identityId":"mkh8LXgOgbEdI8aMaQLFDA","type":"ADD_ALIAS"},"ledgerTimestamp":1675041002878,"uuid":"9QLZ2OzxresmIXBJfAKNNg","version":"1"}
{"action":{"identity":{"address":"N\u0000sourcecred\u0000core\u0000IDENTITY\u000050PPe9GMH6N8cDbXmzvxZA\u0000","aliases":[],"id":"50PPe9GMH6N8cDbXmzvxZA","name":"roneil","subtype":"USER"},"type":"CREATE_IDENTITY"},"ledgerTimestamp":1675041002879,"uuid":"tWDn4e8JH1mKnmfj1g1KGw","version":"1"}
{"action":{"alias":{"address":"N\u0000sourcecred\u0000discord\u0000MEMBER\u0000user\u0000475460021136916481\u0000","description":"discord/roneil#6546"},"identityId":"50PPe9GMH6N8cDbXmzvxZA","type":"ADD_ALIAS"},"ledgerTimestamp":1675041002879,"uuid":"8lanD0yjIRY0aRNCxrTxEQ","version":"1"}
{"action":{"identity":{"address":"N\u0000sourcecred\u0000core\u0000IDENTITY\u0000zRBtdaVI6HKix56bymOnkg\u0000","aliases":[],"id":"zRBtdaVI6HKix56bymOnkg","name":"timetwister","subtype":"USER"},"type":"CREATE_IDENTITY"},"ledgerTimestamp":1675041002879,"uuid":"yqV2bL0moVNQuMyp86Beyg","version":"1"}
{"action":{"alias":{"address":"N\u0000sourcecred\u0000discord\u0000MEMBER\u0000user\u0000476311997441376269\u0000","description":"discord/timetwister#3031"},"identityId":"zRBtdaVI6HKix56bymOnkg","type":"ADD_ALIAS"},"ledgerTimestamp":1675041002879,"uuid":"vFvrkZsOrWV1AnZ5GwH0lw","version":"1"}
{"action":{"identity":{"address":"N\u0000sourcecred\u0000core\u0000IDENTITY\u0000wqY3WXvYcOYIvI927X3mRQ\u0000","aliases":[],"id":"wqY3WXvYcOYIvI927X3mRQ","name":"Drew-Harding","subtype":"USER"},"type":"CREATE_IDENTITY"},"ledgerTimestamp":1675041002879,"uuid":"S46fKBoibq50N8Z3KXWhGw","version":"1"}
{"action":{"alias":{"address":"N\u0000sourcecred\u0000discord\u0000MEMBER\u0000user\u0000476721554311610369\u0000","description":"discord/Drew Harding#2245"},"identityId":"wqY3WXvYcOYIvI927X3mRQ","type":"ADD_ALIAS"},"ledgerTimestamp":1675041002879,"uuid":"dmhVKCbEBMh4Y0UG8EFlqQ","version":"1"}
{"action":{"identity":{"address":"N\u0000sourcecred\u0000core\u0000IDENTITY\u0000SArlASbFzms0LPkkLdMiaA\u0000","aliases":[],"id":"SArlASbFzms0LPkkLdMiaA","name":"atvanguard","subtype":"USER"},"type":"CREATE_IDENTITY"},"ledgerTimestamp":1675041002879,"uuid":"FYvWgfr3EE5lzGE5GKcqMA","version":"1"}
{"action":{"alias":{"address":"N\u0000sourcecred\u0000discord\u0000MEMBER\u0000user\u0000483280542658461696\u0000","description":"discord/atvanguard#1425"},"identityId":"SArlASbFzms0LPkkLdMiaA","type":"ADD_ALIAS"},"ledgerTimestamp":1675041002879,"uuid":"yckLZ9pIJDwB0YtlkYuwmg","version":"1"}
{"action":{"identity":{"address":"N\u0000sourcecred\u0000core\u0000IDENTITY\u0000PAf9OEsjJlqSgm5EggPfkw\u0000","aliases":[],"id":"PAf9OEsjJlqSgm5EggPfkw","name":"oed","subtype":"USER"},"type":"CREATE_IDENTITY"},"ledgerTimestamp":1675041002880,"uuid":"hDnJWrN0j3qgZyobnZ6lig","version":"1"}
{"action":{"alias":{"address":"N\u0000sourcecred\u0000discord\u0000MEMBER\u0000user\u0000486079775165906960\u0000","description":"discord/oed#0829"},"identityId":"PAf9OEsjJlqSgm5EggPfkw","type":"ADD_ALIAS"},"ledgerTimestamp":1675041002880,"uuid":"7qIQMbAl3mu6o25LH9mqHQ","version":"1"}
{"action":{"identity":{"address":"N\u0000sourcecred\u0000core\u0000IDENTITY\u0000I3eWrvlBu5FD5E5JWhA4Lw\u0000","aliases":[],"id":"I3eWrvlBu5FD5E5JWhA4Lw","name":"cami","subtype":"USER"},"type":"CREATE_IDENTITY"},"ledgerTimestamp":1675041002880,"uuid":"TXIWEwdsV8AnH2lcvkrPyA","version":"1"}
{"action":{"alias":{"address":"N\u0000sourcecred\u0000discord\u0000MEMBER\u0000user\u0000509519965569941504\u0000","description":"discord/cami#2252"},"identityId":"I3eWrvlBu5FD5E5JWhA4Lw","type":"ADD_ALIAS"},"ledgerTimestamp":1675041002880,"uuid":"6bzVZFByHBSo7KGJtVO52Q","version":"1"}
{"action":{"identity":{"address":"N\u0000sourcecred\u0000core\u0000IDENTITY\u0000vXf3j3UOxvaWKKrdE6CkHw\u0000","aliases":[],"id":"vXf3j3UOxvaWKKrdE6CkHw","name":"knight4seal","subtype":"USER"},"type":"CREATE_IDENTITY"},"ledgerTimestamp":1675041002880,"uuid":"rteyk4mXkVvKn18WQIKbhw","version":"1"}
{"action":{"alias":{"address":"N\u0000sourcecred\u0000discord\u0000MEMBER\u0000user\u0000513648471924932736\u0000","description":"discord/knight4seal#1232"},"identityId":"vXf3j3UOxvaWKKrdE6CkHw","type":"ADD_ALIAS"},"ledgerTimestamp":1675041002880,"uuid":"NQW3NVi3V5rYj63n8F54sA","version":"1"}
{"action":{"identity":{"address":"N\u0000sourcecred\u0000core\u0000IDENTITY\u0000dcK2Ine2H6P3NB1z9NAbMQ\u0000","aliases":[],"id":"dcK2Ine2H6P3NB1z9NAbMQ","name":"Esteve-Serra-Clavera---FLOC-","subtype":"USER"},"type":"CREATE_IDENTITY"},"ledgerTimestamp":1675041002881,"uuid":"kNQkXrExjKD3KXWM3SMMqA","version":"1"}
{"action":{"alias":{"address":"N\u0000sourcecred\u0000discord\u0000MEMBER\u0000user\u0000521999044017651714\u0000","description":"discord/Esteve Serra Clavera | FLOC*#7762"},"identityId":"dcK2Ine2H6P3NB1z9NAbMQ","type":"ADD_ALIAS"},"ledgerTimestamp":1675041002881,"uuid":"0sw6jSmmewGX1jnFW6AwhA","version":"1"}
{"action":{"identity":{"address":"N\u0000sourcecred\u0000core\u0000IDENTITY\u0000p8qOhgLWSVNIOCbMkWoIeA\u0000","aliases":[],"id":"p8qOhgLWSVNIOCbMkWoIeA","name":"Alex-N---0xCord","subtype":"USER"},"type":"CREATE_IDENTITY"},"ledgerTimestamp":1675041002881,"uuid":"4p8KTdBXubPFQX1peKdxwg","version":"1"}
{"action":{"alias":{"address":"N\u0000sourcecred\u0000discord\u0000MEMBER\u0000user\u0000522158300675047425\u0000","description":"discord/Alex N | 0xCord#8499"},"identityId":"p8qOhgLWSVNIOCbMkWoIeA","type":"ADD_ALIAS"},"ledgerTimestamp":1675041002881,"uuid":"C278PwVNZ2hxK4Fy0QcooQ","version":"1"}
{"action":{"identity":{"address":"N\u0000sourcecred\u0000core\u0000IDENTITY\u0000YAg0t46Sx0nOe2JTbr32fQ\u0000","aliases":[],"id":"YAg0t46Sx0nOe2JTbr32fQ","name":"vengist","subtype":"USER"},"type":"CREATE_IDENTITY"},"ledgerTimestamp":1675041002881,"uuid":"TeNMGwgwRAiVBnSYg4MEyg","version":"1"}
{"action":{"alias":{"address":"N\u0000sourcecred\u0000discord\u0000MEMBER\u0000user\u0000538087853628981259\u0000","description":"discord/vengist#8655"},"identityId":"YAg0t46Sx0nOe2JTbr32fQ","type":"ADD_ALIAS"},"ledgerTimestamp":1675041002881,"uuid":"cPd8zDvj7D5xZW6qK7L5FA","version":"1"}
{"action":{"identity":{"address":"N\u0000sourcecred\u0000core\u0000IDENTITY\u00005ZeAcyFyev1wewYoxoZn6A\u0000","aliases":[],"id":"5ZeAcyFyev1wewYoxoZn6A","name":"lomashuk","subtype":"USER"},"type":"CREATE_IDENTITY"},"ledgerTimestamp":1675041002881,"uuid":"RiON4kW1TLKnXcQGIryIyg","version":"1"}
{"action":{"alias":{"address":"N\u0000sourcecred\u0000discord\u0000MEMBER\u0000user\u0000540909325313507368\u0000","description":"discord/lomashuk#2980"},"identityId":"5ZeAcyFyev1wewYoxoZn6A","type":"ADD_ALIAS"},"ledgerTimestamp":1675041002882,"uuid":"5QU2SnBxoGRNW9idMnM7Xw","version":"1"}
{"action":{"identity":{"address":"N\u0000sourcecred\u0000core\u0000IDENTITY\u0000BgH3OlpWowzEWXOktjhyAQ\u0000","aliases":[],"id":"BgH3OlpWowzEWXOktjhyAQ","name":"rayan","subtype":"USER"},"type":"CREATE_IDENTITY"},"ledgerTimestamp":1675041002882,"uuid":"oSOrkubTGZYPrSGm00Ndmw","version":"1"}
{"action":{"alias":{"address":"N\u0000sourcecred\u0000discord\u0000MEMBER\u0000user\u0000547015176138784768\u0000","description":"discord/rayan#3000"},"identityId":"BgH3OlpWowzEWXOktjhyAQ","type":"ADD_ALIAS"},"ledgerTimestamp":1675041002882,"uuid":"FMG5Pb1nBMiMyzDHwhYjyg","version":"1"}
{"action":{"identity":{"address":"N\u0000sourcecred\u0000core\u0000IDENTITY\u0000TLr9WcokrsApI8yQ1hggDw\u0000","aliases":[],"id":"TLr9WcokrsApI8yQ1hggDw","name":"samkuhlmann","subtype":"USER"},"type":"CREATE_IDENTITY"},"ledgerTimestamp":1675041002882,"uuid":"4P6ELNgy5QD1jCmGkS88HQ","version":"1"}
{"action":{"alias":{"address":"N\u0000sourcecred\u0000discord\u0000MEMBER\u0000user\u0000547240329166848020\u0000","description":"discord/samkuhlmann#3559"},"identityId":"TLr9WcokrsApI8yQ1hggDw","type":"ADD_ALIAS"},"ledgerTimestamp":1675041002882,"uuid":"3nvsbHDujF9qgNACa8el3Q","version":"1"}
{"action":{"identity":{"address":"N\u0000sourcecred\u0000core\u0000IDENTITY\u0000NebnbLVDu0P4EEXNa4Q92Q\u0000","aliases":[],"id":"NebnbLVDu0P4EEXNa4Q92Q","name":"rzurrer","subtype":"USER"},"type":"CREATE_IDENTITY"},"ledgerTimestamp":1675041002883,"uuid":"QPqIAUMybNhpYiOZKKldpg","version":"1"}
{"action":{"alias":{"address":"N\u0000sourcecred\u0000discord\u0000MEMBER\u0000user\u0000559714571548360725\u0000","description":"discord/rzurrer#0067"},"identityId":"NebnbLVDu0P4EEXNa4Q92Q","type":"ADD_ALIAS"},"ledgerTimestamp":1675041002883,"uuid":"5Uq0bPDRrvCoTXgPDYW9iA","version":"1"}
{"action":{"identity":{"address":"N\u0000sourcecred\u0000core\u0000IDENTITY\u0000GWiD4hpF0n6YADjdywZSeA\u0000","aliases":[],"id":"GWiD4hpF0n6YADjdywZSeA","name":"coopahtroopa","subtype":"USER"},"type":"CREATE_IDENTITY"},"ledgerTimestamp":1675041002883,"uuid":"50rOMXcz1GeTea0RYEM2IQ","version":"1"}
{"action":{"alias":{"address":"N\u0000sourcecred\u0000discord\u0000MEMBER\u0000user\u0000560581405050929153\u0000","description":"discord/coopahtroopa#9799"},"identityId":"GWiD4hpF0n6YADjdywZSeA","type":"ADD_ALIAS"},"ledgerTimestamp":1675041002883,"uuid":"V63u28GgBMfy442i6VzQ9Q","version":"1"}
{"action":{"identity":{"address":"N\u0000sourcecred\u0000core\u0000IDENTITY\u00006rezXmvrL4o15KmOgnQZ3Q\u0000","aliases":[],"id":"6rezXmvrL4o15KmOgnQZ3Q","name":"Quentin---Stake-Capital","subtype":"USER"},"type":"CREATE_IDENTITY"},"ledgerTimestamp":1675041002883,"uuid":"9idFZaxVBMPmeVRJoLHZDA","version":"1"}
{"action":{"alias":{"address":"N\u0000sourcecred\u0000discord\u0000MEMBER\u0000user\u0000570339388790276116\u0000","description":"discord/Quentin | Stake Capital#6528"},"identityId":"6rezXmvrL4o15KmOgnQZ3Q","type":"ADD_ALIAS"},"ledgerTimestamp":1675041002884,"uuid":"ME1WniepggXblr8mYpxXbg","version":"1"}
{"action":{"identity":{"address":"N\u0000sourcecred\u0000core\u0000IDENTITY\u0000eK4QfEy8kpNnTv19n6q5EQ\u0000","aliases":[],"id":"eK4QfEy8kpNnTv19n6q5EQ","name":"victorrortvedt","subtype":"USER"},"type":"CREATE_IDENTITY"},"ledgerTimestamp":1675041002884,"uuid":"xkumsnb7TOrCXj4DvCDwSw","version":"1"}
{"action":{"alias":{"address":"N\u0000sourcecred\u0000discord\u0000MEMBER\u0000user\u0000579080647860158475\u0000","description":"discord/victorrortvedt#3874"},"identityId":"eK4QfEy8kpNnTv19n6q5EQ","type":"ADD_ALIAS"},"ledgerTimestamp":1675041002884,"uuid":"7ZAb2RzPNUkdEXUpZvwuEg","version":"1"}
{"action":{"identity":{"address":"N\u0000sourcecred\u0000core\u0000IDENTITY\u0000DHGu6poVszgBUOkg4l0PJQ\u0000","aliases":[],"id":"DHGu6poVszgBUOkg4l0PJQ","name":"JohnPaller---Opolis","subtype":"USER"},"type":"CREATE_IDENTITY"},"ledgerTimestamp":1675041002884,"uuid":"tAS55QB9Fv6Q1YlrCvVhkQ","version":"1"}
{"action":{"alias":{"address":"N\u0000sourcecred\u0000discord\u0000MEMBER\u0000user\u0000582987556954701918\u0000","description":"discord/JohnPaller | Opolis#2670"},"identityId":"DHGu6poVszgBUOkg4l0PJQ","type":"ADD_ALIAS"},"ledgerTimestamp":1675041002884,"uuid":"RHzCJ3zygk2Psv4FvGBOyQ","version":"1"}
{"action":{"identity":{"address":"N\u0000sourcecred\u0000core\u0000IDENTITY\u0000gXtBGkYAFky1Xbm7QkfNVQ\u0000","aliases":[],"id":"gXtBGkYAFky1Xbm7QkfNVQ","name":"mattizee","subtype":"USER"},"type":"CREATE_IDENTITY"},"ledgerTimestamp":1675041002884,"uuid":"Leskp24qMP7cPROhNr1EKw","version":"1"}
{"action":{"alias":{"address":"N\u0000sourcecred\u0000discord\u0000MEMBER\u0000user\u0000585807428436623401\u0000","description":"discord/mattizee#9765"},"identityId":"gXtBGkYAFky1Xbm7QkfNVQ","type":"ADD_ALIAS"},"ledgerTimestamp":1675041002884,"uuid":"u6ph6D14e2oJPbt5c7CQPQ","version":"1"}
{"action":{"identity":{"address":"N\u0000sourcecred\u0000core\u0000IDENTITY\u0000AfnKS7PR3IgXEiKGKkqjlg\u0000","aliases":[],"id":"AfnKS7PR3IgXEiKGKkqjlg","name":"Mark-Pascall","subtype":"USER"},"type":"CREATE_IDENTITY"},"ledgerTimestamp":1675041002885,"uuid":"MvbbJF1p4tKw5U2UaJQvkA","version":"1"}
{"action":{"alias":{"address":"N\u0000sourcecred\u0000discord\u0000MEMBER\u0000user\u0000588876427307253773\u0000","description":"discord/Mark Pascall#1080"},"identityId":"AfnKS7PR3IgXEiKGKkqjlg","type":"ADD_ALIAS"},"ledgerTimestamp":1675041002885,"uuid":"ZUDBpDz2A0WsvlPiPJyLKg","version":"1"}
{"action":{"identity":{"address":"N\u0000sourcecred\u0000core\u0000IDENTITY\u0000U01EuGCWbazbG3b16bDeEw\u0000","aliases":[],"id":"U01EuGCWbazbG3b16bDeEw","name":"EthWarrior","subtype":"USER"},"type":"CREATE_IDENTITY"},"ledgerTimestamp":1675041002885,"uuid":"Kl0OSLVu6roGuKWmRdfkoA","version":"1"}
{"action":{"alias":{"address":"N\u0000sourcecred\u0000discord\u0000MEMBER\u0000user\u0000604982965193146378\u0000","description":"discord/EthWarrior#3346"},"identityId":"U01EuGCWbazbG3b16bDeEw","type":"ADD_ALIAS"},"ledgerTimestamp":1675041002885,"uuid":"c4S8R21Pa8dubX4bxAtlWw","version":"1"}
{"action":{"identity":{"address":"N\u0000sourcecred\u0000core\u0000IDENTITY\u0000CLKLq8yV4SzAgS4iVVGNSg\u0000","aliases":[],"id":"CLKLq8yV4SzAgS4iVVGNSg","name":"Michael-H","subtype":"USER"},"type":"CREATE_IDENTITY"},"ledgerTimestamp":1675041002885,"uuid":"3tNdquG5BU3kRINvjzGNfQ","version":"1"}
{"action":{"alias":{"address":"N\u0000sourcecred\u0000discord\u0000MEMBER\u0000user\u0000605325822043357224\u0000","description":"discord/Michael H#8726"},"identityId":"CLKLq8yV4SzAgS4iVVGNSg","type":"ADD_ALIAS"},"ledgerTimestamp":1675041002885,"uuid":"LxMhmEklLasQHb0ly2X7qA","version":"1"}
{"action":{"identity":{"address":"N\u0000sourcecred\u0000core\u0000IDENTITY\u0000HQZlPPAFvRRKaUVlDlkBVw\u0000","aliases":[],"id":"HQZlPPAFvRRKaUVlDlkBVw","name":"BlockchainJames","subtype":"USER"},"type":"CREATE_IDENTITY"},"ledgerTimestamp":1675041002886,"uuid":"7zwMeRexrTYmFgVo0m2WFw","version":"1"}
{"action":{"alias":{"address":"N\u0000sourcecred\u0000discord\u0000MEMBER\u0000user\u0000621474267988623393\u0000","description":"discord/BlockchainJames#1665"},"identityId":"HQZlPPAFvRRKaUVlDlkBVw","type":"ADD_ALIAS"},"ledgerTimestamp":1675041002886,"uuid":"0ZtnHg75eEqpPmYHwCBm4g","version":"1"}
{"action":{"identity":{"address":"N\u0000sourcecred\u0000core\u0000IDENTITY\u0000Hy5M70W89MKgYH6Yt0ixeQ\u0000","aliases":[],"id":"Hy5M70W89MKgYH6Yt0ixeQ","name":"Callum","subtype":"USER"},"type":"CREATE_IDENTITY"},"ledgerTimestamp":1675041002886,"uuid":"diG1H16oJEiBkiKdLaEzbg","version":"1"}
{"action":{"alias":{"address":"N\u0000sourcecred\u0000discord\u0000MEMBER\u0000user\u0000622930391183130654\u0000","description":"discord/Callum#8721"},"identityId":"Hy5M70W89MKgYH6Yt0ixeQ","type":"ADD_ALIAS"},"ledgerTimestamp":1675041002886,"uuid":"ZNbbEbu3JgsMjpIWNyYyqg","version":"1"}
{"action":{"identity":{"address":"N\u0000sourcecred\u0000core\u0000IDENTITY\u000054JYLDRPczmLkGxtRKD7eg\u0000","aliases":[],"id":"54JYLDRPczmLkGxtRKD7eg","name":"gitpusha","subtype":"USER"},"type":"CREATE_IDENTITY"},"ledgerTimestamp":1675041002886,"uuid":"eaiX70ZmUDKh0kDAh2dOcQ","version":"1"}
{"action":{"alias":{"address":"N\u0000sourcecred\u0000discord\u0000MEMBER\u0000user\u0000640605614757642252\u0000","description":"discord/gitpusha#7509"},"identityId":"54JYLDRPczmLkGxtRKD7eg","type":"ADD_ALIAS"},"ledgerTimestamp":1675041002886,"uuid":"QpxoKmTjgLy2QkIVy7U6qw","version":"1"}
{"action":{"identity":{"address":"N\u0000sourcecred\u0000core\u0000IDENTITY\u0000pmPmGq4tK9TxiabKH4ydNQ\u0000","aliases":[],"id":"pmPmGq4tK9TxiabKH4ydNQ","name":"kevinknielsen---Boardroom","subtype":"USER"},"type":"CREATE_IDENTITY"},"ledgerTimestamp":1675041002887,"uuid":"wDPRpA8VTLhNnpwgHmCZow","version":"1"}
{"action":{"alias":{"address":"N\u0000sourcecred\u0000discord\u0000MEMBER\u0000user\u0000650821519588720651\u0000","description":"discord/kevinknielsen | Boardroom#7885"},"identityId":"pmPmGq4tK9TxiabKH4ydNQ","type":"ADD_ALIAS"},"ledgerTimestamp":1675041002887,"uuid":"dszTEawd3Ky7v9izqaxASQ","version":"1"}
{"action":{"identity":{"address":"N\u0000sourcecred\u0000core\u0000IDENTITY\u0000cJwGyJGLnrZg8KMixwrpUQ\u0000","aliases":[],"id":"cJwGyJGLnrZg8KMixwrpUQ","name":"evgeny---Re7","subtype":"USER"},"type":"CREATE_IDENTITY"},"ledgerTimestamp":1675041002887,"uuid":"856PkBj6yFET0BG2jM7GUg","version":"1"}
{"action":{"alias":{"address":"N\u0000sourcecred\u0000discord\u0000MEMBER\u0000user\u0000656550058812112958\u0000","description":"discord/evgeny | Re7#5721"},"identityId":"cJwGyJGLnrZg8KMixwrpUQ","type":"ADD_ALIAS"},"ledgerTimestamp":1675041002887,"uuid":"AMEWWi8lGPXDJUYf8ymRbQ","version":"1"}
{"action":{"identity":{"address":"N\u0000sourcecred\u0000core\u0000IDENTITY\u0000cAEjhz9o6HJsA64Rf6A16Q\u0000","aliases":[],"id":"cAEjhz9o6HJsA64Rf6A16Q","name":"AlfaBlok","subtype":"USER"},"type":"CREATE_IDENTITY"},"ledgerTimestamp":1675041002887,"uuid":"pJ4ZdlnN8H7od6GggY8XRQ","version":"1"}
{"action":{"alias":{"address":"N\u0000sourcecred\u0000discord\u0000MEMBER\u0000user\u0000664600985959792668\u0000","description":"discord/AlfaBlok#5239"},"identityId":"cAEjhz9o6HJsA64Rf6A16Q","type":"ADD_ALIAS"},"ledgerTimestamp":1675041002887,"uuid":"2N7XaFoZjNnJ3JdmDL6YCQ","version":"1"}
{"action":{"identity":{"address":"N\u0000sourcecred\u0000core\u0000IDENTITY\u0000efxv5RIqiRQWnSjfXWZBXg\u0000","aliases":[],"id":"efxv5RIqiRQWnSjfXWZBXg","name":"HelloShreyas","subtype":"USER"},"type":"CREATE_IDENTITY"},"ledgerTimestamp":1675041002887,"uuid":"EKO3Ndhr6sVm6c89BXgp8w","version":"1"}
{"action":{"alias":{"address":"N\u0000sourcecred\u0000discord\u0000MEMBER\u0000user\u0000678665960349106187\u0000","description":"discord/HelloShreyas#2656"},"identityId":"efxv5RIqiRQWnSjfXWZBXg","type":"ADD_ALIAS"},"ledgerTimestamp":1675041002887,"uuid":"5ZfdcD2iWLWj65JcMAJldA","version":"1"}
{"action":{"identity":{"address":"N\u0000sourcecred\u0000core\u0000IDENTITY\u0000pfaWkWjq70KYXQHeX2A1Tw\u0000","aliases":[],"id":"pfaWkWjq70KYXQHeX2A1Tw","name":"z-sonofwolf","subtype":"USER"},"type":"CREATE_IDENTITY"},"ledgerTimestamp":1675041002888,"uuid":"6j1xaPaEpCJcaAInr0pl5A","version":"1"}
{"action":{"alias":{"address":"N\u0000sourcecred\u0000discord\u0000MEMBER\u0000user\u0000692194585488916531\u0000","description":"discord/z_sonofwolf#2880"},"identityId":"pfaWkWjq70KYXQHeX2A1Tw","type":"ADD_ALIAS"},"ledgerTimestamp":1675041002888,"uuid":"8fXU4xEKG6aENjg82z5DQg","version":"1"}
{"action":{"identity":{"address":"N\u0000sourcecred\u0000core\u0000IDENTITY\u0000mo6cqqFY9D1tloc5twJi6A\u0000","aliases":[],"id":"mo6cqqFY9D1tloc5twJi6A","name":"marinaspin","subtype":"USER"},"type":"CREATE_IDENTITY"},"ledgerTimestamp":1675041002888,"uuid":"ubS4awgubpwrZNUZfPZMDw","version":"1"}
{"action":{"alias":{"address":"N\u0000sourcecred\u0000discord\u0000MEMBER\u0000user\u0000692710298934575207\u0000","description":"discord/marinaspin#4353"},"identityId":"mo6cqqFY9D1tloc5twJi6A","type":"ADD_ALIAS"},"ledgerTimestamp":1675041002888,"uuid":"3zLM5s3Tzf7FVVEkEvppzg","version":"1"}
{"action":{"identity":{"address":"N\u0000sourcecred\u0000core\u0000IDENTITY\u0000x9weZqOqe7JXFAs4viGmwA\u0000","aliases":[],"id":"x9weZqOqe7JXFAs4viGmwA","name":"trentmc0","subtype":"USER"},"type":"CREATE_IDENTITY"},"ledgerTimestamp":1675041002888,"uuid":"MxT5jOirWemonLGGWlkr8A","version":"1"}
{"action":{"alias":{"address":"N\u0000sourcecred\u0000discord\u0000MEMBER\u0000user\u0000694909516285739038\u0000","description":"discord/trentmc0#2875"},"identityId":"x9weZqOqe7JXFAs4viGmwA","type":"ADD_ALIAS"},"ledgerTimestamp":1675041002888,"uuid":"ZYV2v5OudRUEWnDmdjuq2Q","version":"1"}
{"action":{"identity":{"address":"N\u0000sourcecred\u0000core\u0000IDENTITY\u0000uyQYW5ntOkzIAkMA4YtN7w\u0000","aliases":[],"id":"uyQYW5ntOkzIAkMA4YtN7w","name":"Andrey---Opium-Team","subtype":"USER"},"type":"CREATE_IDENTITY"},"ledgerTimestamp":1675041002889,"uuid":"OuqDU0WEfovr2CyeBuAtYg","version":"1"}
{"action":{"alias":{"address":"N\u0000sourcecred\u0000discord\u0000MEMBER\u0000user\u0000696301712863920178\u0000","description":"discord/Andrey | Opium Team#8404"},"identityId":"uyQYW5ntOkzIAkMA4YtN7w","type":"ADD_ALIAS"},"ledgerTimestamp":1675041002889,"uuid":"PXdDkAQMujvll04GxRMoeQ","version":"1"}
{"action":{"identity":{"address":"N\u0000sourcecred\u0000core\u0000IDENTITY\u0000SlTVFvinkaCZvZn8M5Hq8g\u0000","aliases":[],"id":"SlTVFvinkaCZvZn8M5Hq8g","name":"Alex-R-","subtype":"USER"},"type":"CREATE_IDENTITY"},"ledgerTimestamp":1675041002890,"uuid":"PK81111V4PYTKurU4FN6Kw","version":"1"}
{"action":{"alias":{"address":"N\u0000sourcecred\u0000discord\u0000MEMBER\u0000user\u0000697484516410916954\u0000","description":"discord/Alex R.#5447"},"identityId":"SlTVFvinkaCZvZn8M5Hq8g","type":"ADD_ALIAS"},"ledgerTimestamp":1675041002890,"uuid":"O9tYhgCQWMhoi5LdL0GOeQ","version":"1"}
{"action":{"identity":{"address":"N\u0000sourcecred\u0000core\u0000IDENTITY\u0000lYV7hLWgPiRIpz5GYh4fZQ\u0000","aliases":[],"id":"lYV7hLWgPiRIpz5GYh4fZQ","name":"alxfal---Rarible-com","subtype":"USER"},"type":"CREATE_IDENTITY"},"ledgerTimestamp":1675041002891,"uuid":"uYF27G8DRJbKrcjumqwzVg","version":"1"}
{"action":{"alias":{"address":"N\u0000sourcecred\u0000discord\u0000MEMBER\u0000user\u0000699356536904089720\u0000","description":"discord/alxfal | Rarible.com#9225"},"identityId":"lYV7hLWgPiRIpz5GYh4fZQ","type":"ADD_ALIAS"},"ledgerTimestamp":1675041002891,"uuid":"jE8mUdNdVNVHvvMdJJT5wQ","version":"1"}
{"action":{"identity":{"address":"N\u0000sourcecred\u0000core\u0000IDENTITY\u0000WYdmTNb6C84nWVi8BsQA1g\u0000","aliases":[],"id":"WYdmTNb6C84nWVi8BsQA1g","name":"aurelianoBuendia","subtype":"USER"},"type":"CREATE_IDENTITY"},"ledgerTimestamp":1675041002891,"uuid":"4wy7jnQkOX1qaG7I0BYeIw","version":"1"}
{"action":{"alias":{"address":"N\u0000sourcecred\u0000discord\u0000MEMBER\u0000user\u0000699911839542280192\u0000","description":"discord/aurelianoBuendia#4026"},"identityId":"WYdmTNb6C84nWVi8BsQA1g","type":"ADD_ALIAS"},"ledgerTimestamp":1675041002891,"uuid":"m26E7xJtLZ3vlvRz4Dx5oQ","version":"1"}
{"action":{"identity":{"address":"N\u0000sourcecred\u0000core\u0000IDENTITY\u0000MAbNfKwAhVKS69lnspvKsQ\u0000","aliases":[],"id":"MAbNfKwAhVKS69lnspvKsQ","name":"jessewldn","subtype":"USER"},"type":"CREATE_IDENTITY"},"ledgerTimestamp":1675041002892,"uuid":"FZZcOC1dxAzdQVjtY9kLuQ","version":"1"}
{"action":{"alias":{"address":"N\u0000sourcecred\u0000discord\u0000MEMBER\u0000user\u0000704329713375641701\u0000","description":"discord/jessewldn#0299"},"identityId":"MAbNfKwAhVKS69lnspvKsQ","type":"ADD_ALIAS"},"ledgerTimestamp":1675041002892,"uuid":"nHOQdjyprZlc90v48BRKcg","version":"1"}
{"action":{"identity":{"address":"N\u0000sourcecred\u0000core\u0000IDENTITY\u0000EKrKoJgLWcdlorvn4ge0zQ\u0000","aliases":[],"id":"EKrKoJgLWcdlorvn4ge0zQ","name":"-RRR---Raphael---MENTOR","subtype":"USER"},"type":"CREATE_IDENTITY"},"ledgerTimestamp":1675041002892,"uuid":"Q3rjlWzdDy92j4j8WBp3fQ","version":"1"}
{"action":{"alias":{"address":"N\u0000sourcecred\u0000discord\u0000MEMBER\u0000user\u0000717619668638236682\u0000","description":"discord/&#x20BF;RRR - Raphael | MENTOR#8701"},"identityId":"EKrKoJgLWcdlorvn4ge0zQ","type":"ADD_ALIAS"},"ledgerTimestamp":1675041002892,"uuid":"yyAWmEMEefXqOibgf1s0uA","version":"1"}
{"action":{"identity":{"address":"N\u0000sourcecred\u0000core\u0000IDENTITY\u0000X2WmRw0ekWzvCqEqPUzFmA\u0000","aliases":[],"id":"X2WmRw0ekWzvCqEqPUzFmA","name":"yamaaa","subtype":"USER"},"type":"CREATE_IDENTITY"},"ledgerTimestamp":1675041002892,"uuid":"GrVbNh8zN1OPP7D6srBymg","version":"1"}
{"action":{"alias":{"address":"N\u0000sourcecred\u0000discord\u0000MEMBER\u0000user\u0000723402380812746786\u0000","description":"discord/yamaaa#5942"},"identityId":"X2WmRw0ekWzvCqEqPUzFmA","type":"ADD_ALIAS"},"ledgerTimestamp":1675041002892,"uuid":"1ubPkC740DE6ASKwcriMWA","version":"1"}
{"action":{"identity":{"address":"N\u0000sourcecred\u0000core\u0000IDENTITY\u0000vHM3krZVoppkSVzKCvMmww\u0000","aliases":[],"id":"vHM3krZVoppkSVzKCvMmww","name":"davelevinedotcom","subtype":"USER"},"type":"CREATE_IDENTITY"},"ledgerTimestamp":1675041002893,"uuid":"VlCZafAp90eHnB4J7VIoXw","version":"1"}
{"action":{"alias":{"address":"N\u0000sourcecred\u0000discord\u0000MEMBER\u0000user\u0000723927546231521291\u0000","description":"discord/davelevinedotcom#3650"},"identityId":"vHM3krZVoppkSVzKCvMmww","type":"ADD_ALIAS"},"ledgerTimestamp":1675041002893,"uuid":"CGlZcOnFMdngJUkiOeMEuA","version":"1"}
{"action":{"identity":{"address":"N\u0000sourcecred\u0000core\u0000IDENTITY\u0000Yp3RbLN2d35Y7QLO1Kv50g\u0000","aliases":[],"id":"Yp3RbLN2d35Y7QLO1Kv50g","name":"Andrew2","subtype":"USER"},"type":"CREATE_IDENTITY"},"ledgerTimestamp":1675041002893,"uuid":"sLxsyDyi3FW2iRlEZf82hA","version":"1"}
{"action":{"alias":{"address":"N\u0000sourcecred\u0000discord\u0000MEMBER\u0000user\u0000736518095019049010\u0000","description":"discord/Andrew2#5056"},"identityId":"Yp3RbLN2d35Y7QLO1Kv50g","type":"ADD_ALIAS"},"ledgerTimestamp":1675041002893,"uuid":"bncmWnXSkcw5nWtM6uBAyQ","version":"1"}
{"action":{"identity":{"address":"N\u0000sourcecred\u0000core\u0000IDENTITY\u0000Pg7WsYWHXd8DXsVdc4TPMw\u0000","aliases":[],"id":"Pg7WsYWHXd8DXsVdc4TPMw","name":"HausBOT","subtype":"BOT"},"type":"CREATE_IDENTITY"},"ledgerTimestamp":1675041002893,"uuid":"wBnyM4EFm23bBJVGJZhwxQ","version":"1"}
{"action":{"alias":{"address":"N\u0000sourcecred\u0000discord\u0000MEMBER\u0000bot\u0000736999684471521321\u0000","description":"discord/HausBOT#0075"},"identityId":"Pg7WsYWHXd8DXsVdc4TPMw","type":"ADD_ALIAS"},"ledgerTimestamp":1675041002893,"uuid":"5glSBRXKtKly3EG6Rdn3BA","version":"1"}
{"action":{"identity":{"address":"N\u0000sourcecred\u0000core\u0000IDENTITY\u0000irCYpUjh3jV7lzKHAMf00g\u0000","aliases":[],"id":"irCYpUjh3jV7lzKHAMf00g","name":"ropsterner","subtype":"USER"},"type":"CREATE_IDENTITY"},"ledgerTimestamp":1675041002894,"uuid":"NwveZDEqLgbF4pfqIR707g","version":"1"}
{"action":{"alias":{"address":"N\u0000sourcecred\u0000discord\u0000MEMBER\u0000user\u0000745680758969991319\u0000","description":"discord/ropsterner#3420"},"identityId":"irCYpUjh3jV7lzKHAMf00g","type":"ADD_ALIAS"},"ledgerTimestamp":1675041002894,"uuid":"ydBuYWMHy8xn3PrYNmyowg","version":"1"}
{"action":{"identity":{"address":"N\u0000sourcecred\u0000core\u0000IDENTITY\u0000Q5mcovhGK9YrXNVJUKWR4g\u0000","aliases":[],"id":"Q5mcovhGK9YrXNVJUKWR4g","name":"frontierrexplorr","subtype":"USER"},"type":"CREATE_IDENTITY"},"ledgerTimestamp":1675041002894,"uuid":"hn9MBKD6WFVbGw9R66k3YA","version":"1"}
{"action":{"alias":{"address":"N\u0000sourcecred\u0000discord\u0000MEMBER\u0000user\u0000746627923880181835\u0000","description":"discord/frontierrexplorr#4167"},"identityId":"Q5mcovhGK9YrXNVJUKWR4g","type":"ADD_ALIAS"},"ledgerTimestamp":1675041002894,"uuid":"u4YQyw57NLfx2TWtl1LUng","version":"1"}
{"action":{"identity":{"address":"N\u0000sourcecred\u0000core\u0000IDENTITY\u0000aj2ye8nqfVZCNZioqy3Hqw\u0000","aliases":[],"id":"aj2ye8nqfVZCNZioqy3Hqw","name":"Justin","subtype":"USER"},"type":"CREATE_IDENTITY"},"ledgerTimestamp":1675041002894,"uuid":"NaAwwZU4EslFDt9wBZDXmg","version":"1"}
{"action":{"alias":{"address":"N\u0000sourcecred\u0000discord\u0000MEMBER\u0000user\u0000747848299708416050\u0000","description":"discord/Justin#0001"},"identityId":"aj2ye8nqfVZCNZioqy3Hqw","type":"ADD_ALIAS"},"ledgerTimestamp":1675041002894,"uuid":"EmQs7bTvZqTKiVvotjMC8w","version":"1"}
{"action":{"identity":{"address":"N\u0000sourcecred\u0000core\u0000IDENTITY\u0000KSRJPmqzb3RZgZg31GJB4Q\u0000","aliases":[],"id":"KSRJPmqzb3RZgZg31GJB4Q","name":"Accel-XR-----","subtype":"USER"},"type":"CREATE_IDENTITY"},"ledgerTimestamp":1675041002895,"uuid":"yqYOJ9MDPzYjVmrsNeLNqw","version":"1"}
{"action":{"alias":{"address":"N\u0000sourcecred\u0000discord\u0000MEMBER\u0000user\u0000749486305469136976\u0000","description":"discord/Accel XR &#x1F47E;&#x1F579;#5756"},"identityId":"KSRJPmqzb3RZgZg31GJB4Q","type":"ADD_ALIAS"},"ledgerTimestamp":1675041002895,"uuid":"t1mH7JErHk038hyLLZZ5ng","version":"1"}
{"action":{"identity":{"address":"N\u0000sourcecred\u0000core\u0000IDENTITY\u00003V5Er84N2bUMhOpmDmOAtQ\u0000","aliases":[],"id":"3V5Er84N2bUMhOpmDmOAtQ","name":"peter-alt","subtype":"USER"},"type":"CREATE_IDENTITY"},"ledgerTimestamp":1675041002895,"uuid":"p7SdOYJqqklt3URgY92c9w","version":"1"}
{"action":{"alias":{"address":"N\u0000sourcecred\u0000discord\u0000MEMBER\u0000user\u0000749785275445805147\u0000","description":"discord/peter alt#2653"},"identityId":"3V5Er84N2bUMhOpmDmOAtQ","type":"ADD_ALIAS"},"ledgerTimestamp":1675041002895,"uuid":"OHalLGvEPF6QoSBPJ4GpLw","version":"1"}
{"action":{"identity":{"address":"N\u0000sourcecred\u0000core\u0000IDENTITY\u0000mdlo5jCeF81Oh7LTdHMOVg\u0000","aliases":[],"id":"mdlo5jCeF81Oh7LTdHMOVg","name":"yolo-swaggins","subtype":"USER"},"type":"CREATE_IDENTITY"},"ledgerTimestamp":1675041002895,"uuid":"Nl3Cdrrre6A7QOB33YPGeQ","version":"1"}
{"action":{"alias":{"address":"N\u0000sourcecred\u0000discord\u0000MEMBER\u0000user\u0000763804523390304277\u0000","description":"discord/yolo swaggins#9621"},"identityId":"mdlo5jCeF81Oh7LTdHMOVg","type":"ADD_ALIAS"},"ledgerTimestamp":1675041002895,"uuid":"7SDMWqn7xRnpMLbl3nt0CQ","version":"1"}
{"action":{"identity":{"address":"N\u0000sourcecred\u0000core\u0000IDENTITY\u000055OuARfpkVjQI0Qu846A7Q\u0000","aliases":[],"id":"55OuARfpkVjQI0Qu846A7Q","name":"hsin-ju","subtype":"USER"},"type":"CREATE_IDENTITY"},"ledgerTimestamp":1675041002895,"uuid":"YEgKMoIdWuy1JgP4zwJQkQ","version":"1"}
{"action":{"alias":{"address":"N\u0000sourcecred\u0000discord\u0000MEMBER\u0000user\u0000787421626400374785\u0000","description":"discord/hsin-ju#4150"},"identityId":"55OuARfpkVjQI0Qu846A7Q","type":"ADD_ALIAS"},"ledgerTimestamp":1675041002895,"uuid":"OUN8aL8DdgFYhmfwoOK88Q","version":"1"}
{"action":{"identity":{"address":"N\u0000sourcecred\u0000core\u0000IDENTITY\u0000uJyOgWwY8F3NVpS2P4e1aQ\u0000","aliases":[],"id":"uJyOgWwY8F3NVpS2P4e1aQ","name":"DmitriyB","subtype":"USER"},"type":"CREATE_IDENTITY"},"ledgerTimestamp":1675041002896,"uuid":"klyEwnBQ6OSZesmXDHJF6w","version":"1"}
{"action":{"alias":{"address":"N\u0000sourcecred\u0000discord\u0000MEMBER\u0000user\u0000796584907547738132\u0000","description":"discord/DmitriyB#6434"},"identityId":"uJyOgWwY8F3NVpS2P4e1aQ","type":"ADD_ALIAS"},"ledgerTimestamp":1675041002896,"uuid":"dNbJke8XfqElRAiMZQIl8Q","version":"1"}
{"action":{"identity":{"address":"N\u0000sourcecred\u0000core\u0000IDENTITY\u0000KrdXXey5hySBXVcdwQxaxg\u0000","aliases":[],"id":"KrdXXey5hySBXVcdwQxaxg","name":"Federico","subtype":"USER"},"type":"CREATE_IDENTITY"},"ledgerTimestamp":1675041002896,"uuid":"9ZcYqu6IlkLC8xEIGNP7xg","version":"1"}
{"action":{"alias":{"address":"N\u0000sourcecred\u0000discord\u0000MEMBER\u0000user\u0000801227350531899402\u0000","description":"discord/Federico#6082"},"identityId":"KrdXXey5hySBXVcdwQxaxg","type":"ADD_ALIAS"},"ledgerTimestamp":1675041002896,"uuid":"JJDb6NBpmeR7Txu9JMkEcw","version":"1"}
{"action":{"identity":{"address":"N\u0000sourcecred\u0000core\u0000IDENTITY\u0000M1KFW695oOqqymFxnVrCVw\u0000","aliases":[],"id":"M1KFW695oOqqymFxnVrCVw","name":"credbot","subtype":"BOT"},"type":"CREATE_IDENTITY"},"ledgerTimestamp":1675041002896,"uuid":"clevt5kwLRKO0V6m94zNsA","version":"1"}
{"action":{"alias":{"address":"N\u0000sourcecred\u0000discord\u0000MEMBER\u0000bot\u0000810468566796992532\u0000","description":"discord/credbot#8796"},"identityId":"M1KFW695oOqqymFxnVrCVw","type":"ADD_ALIAS"},"ledgerTimestamp":1675041002897,"uuid":"pbc3NxD0uEnXTjB6vF5RAw","version":"1"}
{"action":{"identity":{"address":"N\u0000sourcecred\u0000core\u0000IDENTITY\u0000Y39R25yRJGdAiBUnrzgdYA\u0000","aliases":[],"id":"Y39R25yRJGdAiBUnrzgdYA","name":"Rana-Eshtiagh","subtype":"USER"},"type":"CREATE_IDENTITY"},"ledgerTimestamp":1675041002897,"uuid":"ikewIPfmtBrRwvIqtQV5UA","version":"1"}
{"action":{"alias":{"address":"N\u0000sourcecred\u0000discord\u0000MEMBER\u0000user\u0000819232586496344085\u0000","description":"discord/Rana Eshtiagh#0750"},"identityId":"Y39R25yRJGdAiBUnrzgdYA","type":"ADD_ALIAS"},"ledgerTimestamp":1675041002897,"uuid":"vV7V1qgb8X8rdALrqMlwhw","version":"1"}
{"action":{"identity":{"address":"N\u0000sourcecred\u0000core\u0000IDENTITY\u00009qNKH2BH4VHQNAddKaDaTg\u0000","aliases":[],"id":"9qNKH2BH4VHQNAddKaDaTg","name":"sharifsakr","subtype":"USER"},"type":"CREATE_IDENTITY"},"ledgerTimestamp":1675041002897,"uuid":"D9vJ1bWd3eADjeJCnWsOhw","version":"1"}
{"action":{"alias":{"address":"N\u0000sourcecred\u0000discord\u0000MEMBER\u0000user\u0000847787801503596565\u0000","description":"discord/sharifsakr#9589"},"identityId":"9qNKH2BH4VHQNAddKaDaTg","type":"ADD_ALIAS"},"ledgerTimestamp":1675041002897,"uuid":"eplooxJ4cO0cW5keSBd6Xw","version":"1"}
{"action":{"identity":{"address":"N\u0000sourcecred\u0000core\u0000IDENTITY\u0000y31Yv9lPwv23GOrSLR4kOg\u0000","aliases":[],"id":"y31Yv9lPwv23GOrSLR4kOg","name":"Ivo","subtype":"USER"},"type":"CREATE_IDENTITY"},"ledgerTimestamp":1675041002897,"uuid":"YsW0hpvXwHyKTwABKrayhQ","version":"1"}
{"action":{"alias":{"address":"N\u0000sourcecred\u0000discord\u0000MEMBER\u0000user\u0000870302265334984715\u0000","description":"discord/Ivo#8114"},"identityId":"y31Yv9lPwv23GOrSLR4kOg","type":"ADD_ALIAS"},"ledgerTimestamp":1675041002897,"uuid":"185Au0DDdRxWJjvASlQrjw","version":"1"}
{"action":{"identity":{"address":"N\u0000sourcecred\u0000core\u0000IDENTITY\u0000ZABLouGrxs3uGIMkJl09gw\u0000","aliases":[],"id":"ZABLouGrxs3uGIMkJl09gw","name":"ggnore","subtype":"USER"},"type":"CREATE_IDENTITY"},"ledgerTimestamp":1675041002897,"uuid":"OnsJdjOoBnDprGBbH1UdJA","version":"1"}
{"action":{"alias":{"address":"N\u0000sourcecred\u0000discord\u0000MEMBER\u0000user\u0000884475868943110146\u0000","description":"discord/ggnore#9767"},"identityId":"ZABLouGrxs3uGIMkJl09gw","type":"ADD_ALIAS"},"ledgerTimestamp":1675041002898,"uuid":"SXmZZlSKo8Lsdx8njuQNxA","version":"1"}
{"action":{"identity":{"address":"N\u0000sourcecred\u0000core\u0000IDENTITY\u0000Ej9xXZnWUmNWi98wD5RirA\u0000","aliases":[],"id":"Ej9xXZnWUmNWi98wD5RirA","name":"fabien","subtype":"USER"},"type":"CREATE_IDENTITY"},"ledgerTimestamp":1675041002898,"uuid":"pdluji6SYXmTdJltoJ6XGw","version":"1"}
{"action":{"alias":{"address":"N\u0000sourcecred\u0000discord\u0000MEMBER\u0000user\u0000238307675501232128\u0000","description":"discord/fabien#4765"},"identityId":"Ej9xXZnWUmNWi98wD5RirA","type":"ADD_ALIAS"},"ledgerTimestamp":1675041002898,"uuid":"5MAl9r5F2ajXa74YtgJrHQ","version":"1"}
{"action":{"identity":{"address":"N\u0000sourcecred\u0000core\u0000IDENTITY\u0000ldGhe2VfPdBtWxlqkMqiRg\u0000","aliases":[],"id":"ldGhe2VfPdBtWxlqkMqiRg","name":"Xcessive-Overlord","subtype":"USER"},"type":"CREATE_IDENTITY"},"ledgerTimestamp":1675041002898,"uuid":"LTZAgiB0pon3Jd5eujYXNg","version":"1"}
{"action":{"alias":{"address":"N\u0000sourcecred\u0000discord\u0000MEMBER\u0000user\u0000238452185900253185\u0000","description":"discord/Xcessive Overlord#8108"},"identityId":"ldGhe2VfPdBtWxlqkMqiRg","type":"ADD_ALIAS"},"ledgerTimestamp":1675041002898,"uuid":"kynoNAUkCoYfmJO3W2nmtw","version":"1"}
{"action":{"identity":{"address":"N\u0000sourcecred\u0000core\u0000IDENTITY\u0000kUdNASabpoIvWD9j9KgXHw\u0000","aliases":[],"id":"kUdNASabpoIvWD9j9KgXHw","name":"Simon---Chainflip","subtype":"USER"},"type":"CREATE_IDENTITY"},"ledgerTimestamp":1675041002898,"uuid":"pKiaFRKVD2CyCwCX9AzsBg","version":"1"}
{"action":{"alias":{"address":"N\u0000sourcecred\u0000discord\u0000MEMBER\u0000user\u0000308757659039956993\u0000","description":"discord/Simon | Chainflip#2979"},"identityId":"kUdNASabpoIvWD9j9KgXHw","type":"ADD_ALIAS"},"ledgerTimestamp":1675041002898,"uuid":"7KJDNJptyFWYvDFBzIYlnA","version":"1"}
{"action":{"identity":{"address":"N\u0000sourcecred\u0000core\u0000IDENTITY\u00009IE19yCY44gEQh8MWMXunw\u0000","aliases":[],"id":"9IE19yCY44gEQh8MWMXunw","name":"0xLucas","subtype":"USER"},"type":"CREATE_IDENTITY"},"ledgerTimestamp":1675041002898,"uuid":"z7mYQKXBg6Jv04hEibr2lw","version":"1"}
{"action":{"alias":{"address":"N\u0000sourcecred\u0000discord\u0000MEMBER\u0000user\u0000322210819528196106\u0000","description":"discord/0xLucas#3124"},"identityId":"9IE19yCY44gEQh8MWMXunw","type":"ADD_ALIAS"},"ledgerTimestamp":1675041002898,"uuid":"s541kbueeSwwE5tpFD9JXg","version":"1"}
{"action":{"identity":{"address":"N\u0000sourcecred\u0000core\u0000IDENTITY\u0000vjZLZ6o63OZZ7TlKoWZzSQ\u0000","aliases":[],"id":"vjZLZ6o63OZZ7TlKoWZzSQ","name":"Yalor","subtype":"USER"},"type":"CREATE_IDENTITY"},"ledgerTimestamp":1675041002899,"uuid":"NdvNV2QlXUrQIpApdzKeaw","version":"1"}
{"action":{"alias":{"address":"N\u0000sourcecred\u0000discord\u0000MEMBER\u0000user\u0000360481131029856256\u0000","description":"discord/Yalor#8008"},"identityId":"vjZLZ6o63OZZ7TlKoWZzSQ","type":"ADD_ALIAS"},"ledgerTimestamp":1675041002899,"uuid":"80oYY8g3lqHAU75kdn853w","version":"1"}
{"action":{"identity":{"address":"N\u0000sourcecred\u0000core\u0000IDENTITY\u0000FGndI4zB7gn9kgOaEylQug\u0000","aliases":[],"id":"FGndI4zB7gn9kgOaEylQug","name":"Splidge---Reality-Cards","subtype":"USER"},"type":"CREATE_IDENTITY"},"ledgerTimestamp":1675041002899,"uuid":"wF84bdda0yGWprKMtZ98QQ","version":"1"}
{"action":{"alias":{"address":"N\u0000sourcecred\u0000discord\u0000MEMBER\u0000user\u0000403298188120948746\u0000","description":"discord/Splidge | Reality Cards#7211"},"identityId":"FGndI4zB7gn9kgOaEylQug","type":"ADD_ALIAS"},"ledgerTimestamp":1675041002899,"uuid":"5h0moOojJeO8fdpJ4jCasg","version":"1"}
{"action":{"identity":{"address":"N\u0000sourcecred\u0000core\u0000IDENTITY\u0000Fqk9o6GmUnvJpKAPda2BZw\u0000","aliases":[],"id":"Fqk9o6GmUnvJpKAPda2BZw","name":"wloka","subtype":"USER"},"type":"CREATE_IDENTITY"},"ledgerTimestamp":1675041002900,"uuid":"mqNgmXlrktK2pj6f0v9Szw","version":"1"}
{"action":{"alias":{"address":"N\u0000sourcecred\u0000discord\u0000MEMBER\u0000user\u0000408039049928900608\u0000","description":"discord/wloka#3263"},"identityId":"Fqk9o6GmUnvJpKAPda2BZw","type":"ADD_ALIAS"},"ledgerTimestamp":1675041002900,"uuid":"QNuxJ6yMjJRNRM3LCjwMmg","version":"1"}
{"action":{"identity":{"address":"N\u0000sourcecred\u0000core\u0000IDENTITY\u0000PIy3PXHXbCyZrcxxgziOlw\u0000","aliases":[],"id":"PIy3PXHXbCyZrcxxgziOlw","name":"Richa---Push","subtype":"USER"},"type":"CREATE_IDENTITY"},"ledgerTimestamp":1675041002900,"uuid":"kkoEdlT8ZVnYgB7kXvPhog","version":"1"}
{"action":{"alias":{"address":"N\u0000sourcecred\u0000discord\u0000MEMBER\u0000user\u0000508280625552293900\u0000","description":"discord/Richa | Push#3211"},"identityId":"PIy3PXHXbCyZrcxxgziOlw","type":"ADD_ALIAS"},"ledgerTimestamp":1675041002900,"uuid":"wVrXWN9Ox5iDTLGc2AecNw","version":"1"}
{"action":{"identity":{"address":"N\u0000sourcecred\u0000core\u0000IDENTITY\u0000ZuDYLTVmyyeRc8b9EI6b3g\u0000","aliases":[],"id":"ZuDYLTVmyyeRc8b9EI6b3g","name":"Xenon-Premium","subtype":"BOT"},"type":"CREATE_IDENTITY"},"ledgerTimestamp":1675041002900,"uuid":"l3kmuQN993vMBO5xbhmABQ","version":"1"}
{"action":{"alias":{"address":"N\u0000sourcecred\u0000discord\u0000MEMBER\u0000bot\u0000524652984425250847\u0000","description":"discord/Xenon Premium#2513"},"identityId":"ZuDYLTVmyyeRc8b9EI6b3g","type":"ADD_ALIAS"},"ledgerTimestamp":1675041002900,"uuid":"LNvniO6OUO94bsMGEjA8Ew","version":"1"}
{"action":{"identity":{"address":"N\u0000sourcecred\u0000core\u0000IDENTITY\u00000pJXRw154Swpjvg4LK761g\u0000","aliases":[],"id":"0pJXRw154Swpjvg4LK761g","name":"kojirohirate","subtype":"USER"},"type":"CREATE_IDENTITY"},"ledgerTimestamp":1675041002900,"uuid":"mmWdcXVZwgUnUJx8XZ3SQw","version":"1"}
{"action":{"alias":{"address":"N\u0000sourcecred\u0000discord\u0000MEMBER\u0000user\u0000705926481808982066\u0000","description":"discord/kojirohirate#2530"},"identityId":"0pJXRw154Swpjvg4LK761g","type":"ADD_ALIAS"},"ledgerTimestamp":1675041002900,"uuid":"6jNAdu8sM0lrREvj1Rk0YA","version":"1"}
{"action":{"identity":{"address":"N\u0000sourcecred\u0000core\u0000IDENTITY\u00003PMOMaZLMeg8d2I0CYZr6Q\u0000","aliases":[],"id":"3PMOMaZLMeg8d2I0CYZr6Q","name":"Jes-s---FLOC-","subtype":"USER"},"type":"CREATE_IDENTITY"},"ledgerTimestamp":1675041002900,"uuid":"sMQVtYibVfJVp2RgHmFPgA","version":"1"}
{"action":{"alias":{"address":"N\u0000sourcecred\u0000discord\u0000MEMBER\u0000user\u0000706788194657763379\u0000","description":"discord/Jes&#xFA;s | FLOC*#1418"},"identityId":"3PMOMaZLMeg8d2I0CYZr6Q","type":"ADD_ALIAS"},"ledgerTimestamp":1675041002900,"uuid":"wAGk2SvBsxvK4eJN1pVIJg","version":"1"}
{"action":{"identity":{"address":"N\u0000sourcecred\u0000core\u0000IDENTITY\u0000hmLeRLBlWCrqrO5dUDAQnw\u0000","aliases":[],"id":"hmLeRLBlWCrqrO5dUDAQnw","name":"Javi---FLOC-","subtype":"USER"},"type":"CREATE_IDENTITY"},"ledgerTimestamp":1675041002901,"uuid":"zdQMtvCJBLLaPmdTvv9t7Q","version":"1"}
{"action":{"alias":{"address":"N\u0000sourcecred\u0000discord\u0000MEMBER\u0000user\u0000713332855123738677\u0000","description":"discord/Javi | FLOC*#1188"},"identityId":"hmLeRLBlWCrqrO5dUDAQnw","type":"ADD_ALIAS"},"ledgerTimestamp":1675041002901,"uuid":"FYqOoTZkqpmWgL9jPUzpFw","version":"1"}
{"action":{"identity":{"address":"N\u0000sourcecred\u0000core\u0000IDENTITY\u0000oV8y8a9uBS1cDJRzRc0J0g\u0000","aliases":[],"id":"oV8y8a9uBS1cDJRzRc0J0g","name":"lemp-eth---MST","subtype":"USER"},"type":"CREATE_IDENTITY"},"ledgerTimestamp":1675041002901,"uuid":"gpjLyJl2KRV66uLB4KrRkw","version":"1"}
{"action":{"alias":{"address":"N\u0000sourcecred\u0000discord\u0000MEMBER\u0000user\u0000736601174593241198\u0000","description":"discord/lemp.eth | MST#8816"},"identityId":"oV8y8a9uBS1cDJRzRc0J0g","type":"ADD_ALIAS"},"ledgerTimestamp":1675041002901,"uuid":"7kxq63C79f8TLyq52v1mSA","version":"1"}
{"action":{"identity":{"address":"N\u0000sourcecred\u0000core\u0000IDENTITY\u0000zguvOJdlVwx1WeKKq05F9g\u0000","aliases":[],"id":"zguvOJdlVwx1WeKKq05F9g","name":"amphiboly","subtype":"USER"},"type":"CREATE_IDENTITY"},"ledgerTimestamp":1675041002902,"uuid":"ONQFPdlL9GiQdqalIaalkQ","version":"1"}
{"action":{"alias":{"address":"N\u0000sourcecred\u0000discord\u0000MEMBER\u0000user\u0000862918193530011688\u0000","description":"discord/amphiboly#4329"},"identityId":"zguvOJdlVwx1WeKKq05F9g","type":"ADD_ALIAS"},"ledgerTimestamp":1675041002903,"uuid":"5vRUYQv8n1qJj0A4pAT5YA","version":"1"}
{"action":{"identity":{"address":"N\u0000sourcecred\u0000core\u0000IDENTITY\u0000qGmYfoytJkXa37tPy9L2Xw\u0000","aliases":[],"id":"qGmYfoytJkXa37tPy9L2Xw","name":"0xMikey---1kx","subtype":"USER"},"type":"CREATE_IDENTITY"},"ledgerTimestamp":1675041002903,"uuid":"5T1ZPku4RZgY6B4tYKyxAA","version":"1"}
{"action":{"alias":{"address":"N\u0000sourcecred\u0000discord\u0000MEMBER\u0000user\u0000895050487324377128\u0000","description":"discord/0xMikey | 1kx#5472"},"identityId":"qGmYfoytJkXa37tPy9L2Xw","type":"ADD_ALIAS"},"ledgerTimestamp":1675041002903,"uuid":"xQRsEMLviDY6xly3EmCq3Q","version":"1"}
{"action":{"identity":{"address":"N\u0000sourcecred\u0000core\u0000IDENTITY\u0000WiXkWjsl0HZ2rqZSNbRCAg\u0000","aliases":[],"id":"WiXkWjsl0HZ2rqZSNbRCAg","name":"YayAreaMama","subtype":"USER"},"type":"CREATE_IDENTITY"},"ledgerTimestamp":1675041002903,"uuid":"yNWOOkoFXxqGQfjAhPYoQQ","version":"1"}
{"action":{"alias":{"address":"N\u0000sourcecred\u0000discord\u0000MEMBER\u0000user\u0000899326363616563251\u0000","description":"discord/YayAreaMama#2486"},"identityId":"WiXkWjsl0HZ2rqZSNbRCAg","type":"ADD_ALIAS"},"ledgerTimestamp":1675041002903,"uuid":"XJ1djkIBKl8GWwFA9Q2mTQ","version":"1"}
{"action":{"identity":{"address":"N\u0000sourcecred\u0000core\u0000IDENTITY\u0000XvjsXqxp5KlBLJlomTopfw\u0000","aliases":[],"id":"XvjsXqxp5KlBLJlomTopfw","name":"Leti---FLOC-","subtype":"USER"},"type":"CREATE_IDENTITY"},"ledgerTimestamp":1675041002904,"uuid":"9lPgaurvOxDPMVBK3YGGRg","version":"1"}
{"action":{"alias":{"address":"N\u0000sourcecred\u0000discord\u0000MEMBER\u0000user\u0000902838164916408330\u0000","description":"discord/Leti | FLOC*#4616"},"identityId":"XvjsXqxp5KlBLJlomTopfw","type":"ADD_ALIAS"},"ledgerTimestamp":1675041002904,"uuid":"9Qa0UvG5xGbwEmUv4wH6WA","version":"1"}
{"action":{"identity":{"address":"N\u0000sourcecred\u0000core\u0000IDENTITY\u0000vZnbQOqEy8TBOtms8AooFg\u0000","aliases":[],"id":"vZnbQOqEy8TBOtms8AooFg","name":"Sobol","subtype":"BOT"},"type":"CREATE_IDENTITY"},"ledgerTimestamp":1675041002905,"uuid":"T6WJAK50SMEXDgJxQEKc1w","version":"1"}
{"action":{"alias":{"address":"N\u0000sourcecred\u0000discord\u0000MEMBER\u0000bot\u0000914954766038208553\u0000","description":"discord/Sobol#9107"},"identityId":"vZnbQOqEy8TBOtms8AooFg","type":"ADD_ALIAS"},"ledgerTimestamp":1675041002905,"uuid":"TrfBuEGOtOVrABWoH5nUlw","version":"1"}
{"action":{"identity":{"address":"N\u0000sourcecred\u0000core\u0000IDENTITY\u0000djvAzS0mVp214SOotg8L7A\u0000","aliases":[],"id":"djvAzS0mVp214SOotg8L7A","name":"YayAreaMama-discord","subtype":"USER"},"type":"CREATE_IDENTITY"},"ledgerTimestamp":1675041002905,"uuid":"EKLv43u472Qlq5oGhkeodQ","version":"1"}
{"action":{"alias":{"address":"N\u0000sourcecred\u0000discord\u0000MEMBER\u0000user\u0000976201379045605466\u0000","description":"discord/YayAreaMama#6545"},"identityId":"djvAzS0mVp214SOotg8L7A","type":"ADD_ALIAS"},"ledgerTimestamp":1675041002905,"uuid":"qNkburSx6j9Mn5G0aLUzKA","version":"1"}
{"action":{"identity":{"address":"N\u0000sourcecred\u0000core\u0000IDENTITY\u0000dBGwE28gWdbyA2Rqeix9PA\u0000","aliases":[],"id":"dBGwE28gWdbyA2Rqeix9PA","name":"SourceCred","subtype":"PROJECT"},"type":"CREATE_IDENTITY"},"ledgerTimestamp":1675041003227,"uuid":"h6NsQsWuExo52vXHRJwQrA","version":"1"}
{"action":{"identityId":"dBGwE28gWdbyA2Rqeix9PA","type":"TOGGLE_ACTIVATION"},"ledgerTimestamp":1675041003227,"uuid":"FV8vFOJBLQpnCLB8aTZM8g","version":"1"}
